<?xml version="1.0" encoding="utf-8"?><!DOCTYPE Regulation PUBLIC "-//Justice Canada//DTD Regulation v1.2.2//EN" "Dtd/Regulations/Version_1.2.2/regulation.dtd"><Regulation gazette-part="II" regulation-type="SOR" xml:lang="en"><Identification><InstrumentNumber>SOR/82-550</InstrumentNumber><RegistrationDate><Date><YYYY>1982</YYYY><MM>5</MM><DD>28</DD></Date></RegistrationDate><ConsolidationDate><Date><YYYY>2018</YYYY><MM>06</MM><DD>21</DD></Date></ConsolidationDate><LastModifiedDate><Date><YYYY>2011</YYYY><MM>5</MM><DD>18</DD></Date></LastModifiedDate><EnablingAuthority><XRefExternal reference-type="act">FINANCIAL ADMINISTRATION ACT</XRefExternal></EnablingAuthority><ShortTitle>Canadian Films and Video Tapes Certification Fees Order</ShortTitle><LongTitle>Order Prescribing the Fees to be Paid by Persons in the Private Sector for Services Provided in Relation to the Certification of Canadian Films and Video Tapes</LongTitle></Identification><Order><Provision format-ref="indent-0-0" language-align="yes"><Text>The Minister of Communications, pursuant to paragraph 13(b) of the <XRefExternal reference-type="act">Financial Administration Act</XRefExternal> and Order in Council P.C. 1982-1394 of 6 May, 1982<FootnoteRef idref="fn_1e">*</FootnoteRef>, hereby makes the annexed <XRefExternal reference-type="regulation">Order prescribing the fees to be paid by persons in the private sector for services provided in relation to the certification of Canadian Films and video tapes</XRefExternal>.</Text><Footnote id="fn_1e" placement="page" status="official"><Label>*</Label><Text>SI/82-104, 1982 <XRefExternal reference-type="other">Canada Gazette</XRefExternal> Part II, p. 1931</Text></Footnote></Provision><Provision format-ref="indent-0-0" language-align="yes"><Text>Dated at Ottawa, May 28, 1982</Text></Provision><Provision format-ref="indent-0-0" language-align="yes"><SignatureBlock justification="right" width="15pc"><SignatureName justification="right" topmarginspacing="8">FRANCIS FOX</SignatureName><SignatureTitle justification="right"><Emphasis style="italic">Minister of Communications</Emphasis></SignatureTitle></SignatureBlock></Provision></Order><Body><Heading level="1"><TitleText>Short Title</TitleText></Heading><Section><Label>1</Label><Text>This Order may be cited as the <XRefExternal reference-type="regulation">Canadian Films and Video Tapes Certification Fees Order</XRefExternal>.</Text></Section><Heading level="1"><TitleText>Interpretation</TitleText></Heading><Section><Label>2</Label><Text>In this Order,</Text><Definition generate-in-text="no"><Text><DefinedTermEn>certification service</DefinedTermEn> means a service provided with respect to an advance ruling, a provisional approval or a certificate given or issued with respect to the certification of films or tapes; (<DefinedTermFr>service d’émission de visas</DefinedTermFr>)</Text></Definition><Definition generate-in-text="no"><Text><DefinedTermEn>feature production</DefinedTermEn> means a motion picture film or tape of not less than 75 minutes running time; (<DefinedTermFr>production long métrage</DefinedTermFr>)</Text></Definition><Definition generate-in-text="no"><Text><DefinedTermEn>film or tape</DefinedTermEn> means a film or tape referred to in subsection 1104(2) of the <XRefExternal reference-type="regulation">Income Tax Regulations</XRefExternal>; (<DefinedTermFr>film ou bande magnétoscopique</DefinedTermFr>)</Text></Definition><Definition generate-in-text="no"><Text><DefinedTermEn>film or tape production budget</DefinedTermEn> means</Text><Paragraph><Label>(a)</Label><Text>where a film or tape is produced by a person in the private sector, the total financial contribution of that person to the production,</Text></Paragraph><Paragraph><Label>(b)</Label><Text>where a film or tape is co-produced under an agreement entered into between Canada and another country, the total financial contribution of Canadian producers to the co-production covered by the agreement, or</Text></Paragraph><Paragraph><Label>(c)</Label><Text>where a film or tape is co-produced by persons in the private sector and by the public sector, the total financial contribution of the persons in the private sector to the co-production; (<DefinedTermFr>budget de production du film ou de la bande magnétoscopique</DefinedTermFr>)</Text></Paragraph></Definition><Definition generate-in-text="no"><Text><DefinedTermEn>Minister</DefinedTermEn> means the Minister of Communications; (<DefinedTermFr>ministre</DefinedTermFr>)</Text></Definition><Definition generate-in-text="no"><Text><DefinedTermEn>review of a certification service</DefinedTermEn> means the review of a certification service undertaken by the Minister where the Minister has indicated in writing his intention to deny the certification; (<DefinedTermFr>révision d’un service d’émission de visas</DefinedTermFr>)</Text></Definition><Definition generate-in-text="no"><Text><DefinedTermEn>short production</DefinedTermEn> means a motion picture film or tape of less than 75 minutes running time. (<DefinedTermFr>production court métrage</DefinedTermFr>)</Text></Definition></Section><Heading level="1"><TitleText>Fees</TitleText></Heading><Section><Label>3</Label><Subsection><Label>(1)</Label><Text>Subject to subsection (2), the fee payable by a person in the private sector who applies for a certification service shall be equal to one thousandth of the film production budget.</Text></Subsection><Subsection><Label>(2)</Label><Text>The fee payable pursuant to subsection (1) shall not be less than $25 or more than $500.</Text></Subsection></Section><Section><Label>4</Label><Text>The fee payable by a person in the private sector who applies for a review of a certification service shall be</Text><Paragraph><Label>(a)</Label><Text>$500 with respect to a short production; and</Text></Paragraph><Paragraph><Label>(b)</Label><Text>$1,500 with respect to a feature production.</Text></Paragraph></Section></Body></Regulation>