<?xml version="1.0" encoding="utf-8"?><!DOCTYPE Regulation PUBLIC "-//Justice Canada//DTD Regulation v1.2.2//EN" "Dtd/Regulations/Version_1.2.2/regulation.dtd"><Regulation gazette-part="II" regulation-type="SOR" xml:lang="en"><Identification><InstrumentNumber>SOR/2003-307</InstrumentNumber><RegistrationDate><Date><YYYY>2003</YYYY><MM>8</MM><DD>20</DD></Date></RegistrationDate><ConsolidationDate><Date><YYYY>2018</YYYY><MM>06</MM><DD>21</DD></Date></ConsolidationDate><LastModifiedDate><Date><YYYY>2010</YYYY><MM>1</MM><DD>26</DD></Date></LastModifiedDate><EnablingAuthority><XRefExternal reference-type="act">CANADIAN ENVIRONMENTAL PROTECTION ACT, 1999</XRefExternal></EnablingAuthority><LongTitle>Environmental Emergency Regulations</LongTitle><RegulationMakerOrder><RegulationMaker>P.C.</RegulationMaker><OrderNumber>2003-1293 </OrderNumber><Date><YYYY> 2003</YYYY><MM>8</MM><DD>20</DD></Date></RegulationMakerOrder></Identification><Order><Provision format-ref="indent-0-0" language-align="yes" list-item="no"><Text>Whereas, pursuant to subsection 332(1) of the <XRefExternal reference-type="act">Canadian Environmental Protection Act, 1999</XRefExternal><FootnoteRef idref="footnotea_e">a</FootnoteRef>, the Minister of the Environment published in the <XRefExternal reference-type="other">Canada Gazette</XRefExternal>, Part I, on August 10, 2002, a copy of the proposed <XRefExternal reference-type="regulation">Environmental Emergency Regulations</XRefExternal>, substantially in the form set out in the annexed Regulations, and persons were given an opportunity to file comments with respect to the proposed Regulations or to file a notice of objection requesting that a board of review be established and stating the reasons for the objection;</Text></Provision><Provision format-ref="indent-0-0" language-align="yes" list-item="no"><Text>And whereas, pursuant to subsection 200(1) of that Act, the National Advisory Committee has been given an opportunity to provide its advice under section 6 of that Act;</Text></Provision><Provision format-ref="indent-0-0" language-align="yes" list-item="no"><Text>Therefore, Her Excellency the Governor General in Council, on the recommendation of the Minister of the Environment, pursuant to subsection 200(1) of the <XRefExternal reference-type="act">Canadian Environmental Protection Act, 1999</XRefExternal><FootnoteRef idref="footnotea_e">a</FootnoteRef>, hereby makes the annexed <XRefExternal reference-type="regulation">Environmental Emergency Regulations</XRefExternal>.</Text><Footnote id="footnotea_e" placement="page" status="official"><Label>a</Label><Text>S.C. 1999, c. 33</Text></Footnote></Provision></Order><Body><Heading level="1"><TitleText>Interpretation</TitleText></Heading><Section><Label>1</Label><Text>The following definitions apply in these Regulations.</Text><Definition generate-in-text="no"><Text><DefinedTermEn>Act</DefinedTermEn> means the <XRefExternal reference-type="act">Canadian Environmental Protection Act, 1999</XRefExternal>. (<DefinedTermFr>Loi</DefinedTermFr>)</Text></Definition><Definition generate-in-text="no"><Text><DefinedTermEn>CAS registry number</DefinedTermEn> means the identification number assigned to a substance by the <XRefExternal reference-type="other">Chemical Abstracts Service Division of the American Chemical Society</XRefExternal>. (<DefinedTermFr>numéro d’enregistrement CAS</DefinedTermFr>)</Text></Definition><Definition generate-in-text="no"><Text><DefinedTermEn>environmental emergency plan</DefinedTermEn> means a plan respecting the prevention of, preparedness for, response to and recovery from an environmental emergency in respect of a substance. (<DefinedTermFr>plan d’urgence environnementale</DefinedTermFr>)</Text></Definition></Section><Heading level="1"><TitleText>List of Substances</TitleText></Heading><Section><Label>2</Label><Text>For the purposes of the definition <DefinedTermEn>substance</DefinedTermEn> in section 193 of the Act, the list of substances consists of the substances set out in column 1 of Schedule 1 in their pure form or in a mixture that has a concentration equal to or greater than the applicable concentration set out in column 2 but does not include</Text><Paragraph><Label>(a)</Label><Text>a substance set out in column 1 of Part 1 of Schedule 1 that is a component of a mixture that has a flash point equal to or greater than 23°C or a boiling point equal to or greater than 35°C;</Text></Paragraph><Paragraph><Label>(b)</Label><Text>a substance set out in column 1 of Part 2 of Schedule 1 when the substance is a gas or a liquid that is a component of a mixture and the partial pressure of the substance is equal to or less than 10 mm of mercury;</Text></Paragraph><Paragraph><Label>(c)</Label><Text>a substance set out in column 1 of Part 1 of Schedule 1 that is a component of natural gas in its gaseous form;</Text></Paragraph><Paragraph><Label>(d)</Label><Text>a substance that is subject to the <XRefExternal reference-type="act">Transportation of Dangerous Goods Act, 1992</XRefExternal> or the <XRefExternal reference-type="act">Canada Shipping Act, 2001</XRefExternal>, unless the substance is being loaded or unloaded at a facility; and</Text></Paragraph><Paragraph><Label>(e)</Label><Text>solid nickel oxide in particles that measure more than 10 μm (microns) in diameter.</Text></Paragraph><HistoricalNote>SOR/2011-294, s. 1.</HistoricalNote></Section><Heading level="1"><TitleText>Identification of Places</TitleText></Heading><Section><Label>3</Label><Subsection><Label>(1)</Label><Text>Any person who owns or has the charge, management or control of a substance set out in column 1 of Schedule 1 that is located at a place in Canada, must submit to the Minister a notice containing the information requested in Schedule 2 for each such place in either of the following circumstances:</Text><Paragraph><Label>(a)</Label><Text>the substance is in a quantity that at any time is equal to or exceeds the quantity set out in column 3 of Schedule 1 for that substance; or</Text></Paragraph><Paragraph><Label>(b)</Label><Text>the substance is in a quantity that is greater than zero and is stored in a container that has a maximum capacity equal to or exceeding the quantity set out in column 3 of Schedule 1 for that substance.</Text></Paragraph></Subsection><Subsection><Label>(2)</Label><Text>In determining quantity for the purposes of subsection (1), the person must include all quantities of the substance that are located at the place, whether in storage or in use, except the following:</Text><Paragraph><Label>(a)</Label><Text>quantities of the substance that are temporarily stored for 72 hours or less in a container not normally located at the place, if the person keeps evidence during the temporary storage period of the date the substance was received;</Text></Paragraph><Paragraph><Label>(b)</Label><Text>quantities of the substance in a container that has a maximum capacity of 30 kg or less;</Text></Paragraph><Paragraph><Label>(c)</Label><Text>quantities of the substance when it is a component of another substance set out in column 1 of Schedule 1;</Text></Paragraph><Paragraph><Label>(d)</Label><Text><Repealed>[Repealed, SOR/2011-294, s. 2]</Repealed></Text></Paragraph><Paragraph><Label>(e)</Label><Text>quantities of the substance in a fuel tank that supplies the engine of a conveyance that is used for transportation;</Text></Paragraph><Paragraph><Label>(f)</Label><Text>quantities of the substance that are found in slag, waste rock in tailings, solid residues, ores and ore concentrates;</Text></Paragraph><Paragraph><Label>(g)</Label><Text>in the case of the substances set out in column 1 of Part 2 of Schedule 1 and bearing CAS registry number 7664-41-7, namely, anhydrous ammonia and ammonia solution, the quantities of those substances that are stored by a farmer and used by them as an agricultural nutrient; and</Text></Paragraph><Paragraph><Label>(h)</Label><Text>in the case of the substance set out in column 1 of Part 1 of Schedule 1 and bearing CAS registry number 74-98-6, namely, propane, the quantity that is in a storage container that has a maximum capacity of less than 10 t and is located at a distance of at least 360 m from the boundaries of the property on which it is located.</Text></Paragraph></Subsection><Subsection><Label>(3)</Label><Text>The person must submit the notice within 90 days after the later of</Text><Paragraph><Label>(a)</Label><Text>the day on which these Regulations come into force, and</Text></Paragraph><Paragraph><Label>(b)</Label><Text>the day on which either of the circumstances under paragraph (1)(a) or (b) first occurs.</Text></Paragraph></Subsection><Subsection><Label>(4)</Label><Text>The person must resubmit the notice referred to in subsection (1) within 60 days after the occurrence of any of the following changes:</Text><Paragraph><Label>(a)</Label><Text>any change to the information provided to the Minister under section 1 or 2 of Schedule 2; or</Text></Paragraph><Paragraph><Label>(b)</Label><Text>any increase of 10% or more in the maximum expected quantity of a substance reported under paragraph 3(d) of Schedule 2.</Text></Paragraph></Subsection><Subsection><Label>(5)</Label><Text>The person must notify the Minister within 90 days after the quantity of the substance located at the place or the maximum capacity of the largest container in which the substance is stored, has for 12 consecutive months been less than the quantity set out for the substance in column 3 of Schedule 1.</Text></Subsection><Subsection><Label>(5.1)</Label><Text>A person who intends to close or decommission a facility or place where the substance is located for any purpose other than maintenance must send a notice to the Minister at least 30 days before the closure or decommissioning of the facility or place, or as soon as feasible in the case of extraordinary circumstances such as fire, major accident, vandalism, natural disaster or act of terrorism, and the notice must contain the information referred to in Schedule 6.</Text></Subsection><Subsection><Label>(6)</Label><Text>At the same time as a person submits information required under subsection (1), (4), (5) or (5.1), the person must submit to the Minister, in the form set out in Schedule 3, a certification that the information contained in the notice is accurate and complete and that is signed by the person or a duly authorized representative.</Text></Subsection><HistoricalNote>SOR/2011-294, s. 2.</HistoricalNote></Section><Heading level="1"><TitleText>Environmental Emergency Plan</TitleText></Heading><Section><Label>4</Label><Subsection><Label>(1)</Label><Text>Subject to section 7, a person required to submit a notice to the Minister under subsection 3(1) must prepare an environmental emergency plan with respect to the substance referred to in that subsection in the following circumstances:</Text><Paragraph><Label>(a)</Label><Text>if the substance is set out in column 1 of Part 1 of Schedule 1 and is not part of a mixture, and</Text><Subparagraph><Label>(i)</Label><Text>the maximum expected quantity of the substance that was reported under paragraph 3(d) of Schedule 2 is equal to or exceeds the quantity set out in column 3 of Schedule 1 for that substance, and</Text></Subparagraph><Subparagraph><Label>(ii)</Label><Text>the substance is in a storage container that has a maximum capacity equal to or exceeding the quantity set out in column 3 of Schedule 1;</Text></Subparagraph></Paragraph><Paragraph><Label>(b)</Label><Text>if the substance is set out in column 1 of Part 1 of Schedule 1 and is a component in a mixture, other than a mixture that is a substance set out in column 1 of Schedule 1, and</Text><Subparagraph><Label>(i)</Label><Text>the mixture is in a quantity that is equal to or exceeds 4.5 tonnes, and</Text></Subparagraph><Subparagraph><Label>(ii)</Label><Text>the mixture is in a storage container that has a maximum capacity equal to or exceeding 4.5 tonnes;</Text></Subparagraph></Paragraph><Paragraph><Label>(c)</Label><Text>if the substance is set out in column 1 of Part 2 of Schedule 1, and</Text><Subparagraph><Label>(i)</Label><Text>the maximum expected quantity of the substance that was reported under paragraph 3(d) of Schedule 2 is equal to or exceeds the quantity set out in column 3 of Schedule 1 for that substance, and</Text></Subparagraph><Subparagraph><Label>(ii)</Label><Text>the substance is in a storage container that has a maximum capacity equal to or exceeding the quantity set out in column 3 of Schedule 1 for that substance; and</Text></Subparagraph></Paragraph><Paragraph><Label>(d)</Label><Text>if the substance is set out in column 1 of Part 3 of Schedule 1, and</Text><Subparagraph><Label>(i)</Label><Text>the maximum expected quantity of the substance that was reported under paragraph 3(d) of Schedule 2 is equal to or exceeds the quantity set out in column 3 of Schedule 1 for that substance, and</Text></Subparagraph><Subparagraph><Label>(ii)</Label><Text>the substance is in a storage container that has a maximum capacity equal to or greater than the quantity set out in column 3 of Schedule 1 for that substance.</Text></Subparagraph></Paragraph></Subsection><Subsection><Label>(2)</Label><Text>In preparing an environmental emergency plan with respect to a substance, the person must consider the following factors:</Text><Paragraph><Label>(a)</Label><Text>the properties and characteristics of the substance and the maximum expected quantity of the substance at the place at any time during a calendar year;</Text></Paragraph><Paragraph><Label>(b)</Label><Text>the commercial, manufacturing, processing or other activity in relation to which the plan is to be prepared;</Text></Paragraph><Paragraph><Label>(c)</Label><Text>the characteristics of the place where the substance is located and of the surrounding area that may increase the risk of harm to the environment or of danger to human life or health; and</Text></Paragraph><Paragraph><Label>(d)</Label><Text>the potential consequences from an environmental emergency on the environment and on human life or health.</Text></Paragraph></Subsection><Subsection><Label>(3)</Label><Text>The environmental emergency plan must include:</Text><Paragraph><Label>(a)</Label><Text>a description of the factors considered under subsection (2);</Text></Paragraph><Paragraph><Label>(b)</Label><Text>the identification of any environmental emergency that can reasonably be expected to occur at the place and that would likely cause harm to the environment or constitute a danger to human life or health, and identification of the harm or danger;</Text></Paragraph><Paragraph><Label>(c)</Label><Text>a description of the measures to be used to prevent, prepare for, respond to and recover from any environmental emergency identified under paragraph (b);</Text></Paragraph><Paragraph><Label>(d)</Label><Text>a list of the individuals who are to carry into effect the plan in the event of an environmental emergency and a description of their roles and responsibilities;</Text></Paragraph><Paragraph><Label>(e)</Label><Text>the identification of the training required for each of the individuals listed under paragraph (d);</Text></Paragraph><Paragraph><Label>(f)</Label><Text>a list of the emergency response equipment included as part of the environmental emergency plan, and the equipment’s location; and</Text></Paragraph><Paragraph><Label>(g)</Label><Text>a description of the measures to be taken by the person referred to in subsection (1) to notify members of the public who may be adversely affected by an environmental emergency and to inform them of those measures and of what to do in the event of an environmental emergency.</Text></Paragraph></Subsection><Subsection><Label>(4)</Label><Text>For each place, the person must submit to the Minister a report containing the information requested in Schedule 4 within six months after the later of</Text><Paragraph><Label>(a)</Label><Text>the day on which these Regulations come into force, and</Text></Paragraph><Paragraph><Label>(b)</Label><Text>the day on which the person is first required to prepare an environmental emergency plan under subsection (1).</Text></Paragraph></Subsection><Subsection><Label>(5)</Label><Text>At the same time as a person submits the report under subsection (4), the person shall submit to the Minister, in the form set out in Schedule 3, a certification that the information contained in the report is accurate and complete, signed by the person or a duly authorized representative.</Text></Subsection><HistoricalNote>SOR/2011-294, s. 3.</HistoricalNote></Section><Section><Label>5</Label><Subsection><Label>(1)</Label><Text>A person referred to in subsection 4(1) must implement and test the environmental emergency plan referred to in section 4 or 7 and submit a notice to the Minister with the information requested in Schedule 5 within one year after the later of</Text><Paragraph><Label>(a)</Label><Text>the day on which these Regulations come into force, and</Text></Paragraph><Paragraph><Label>(b)</Label><Text>the day on which the person is first required to prepare an environmental emergency plan under subsection 4(1).</Text></Paragraph></Subsection><Subsection><Label>(2)</Label><Text>At the same time as the person submits the notice under subsection (1), the person must submit to the Minister, in the form set out in Schedule 3, a certification that states that the information contained in the notice is accurate and complete and that is signed by the person or a duly authorized representative.</Text></Subsection><HistoricalNote>SOR/2011-294, s. 4(E).</HistoricalNote></Section><Section><Label>6</Label><Subsection><Label>(1)</Label><Text>The person referred to in subsection 5(1) must update and test the environmental emergency plan at least once each calendar year to ensure that it continues to meet the requirements of subsections 4(2) and (3).</Text></Subsection><Subsection><Label>(2)</Label><Text>The person must keep a copy of the plan readily available for the individuals who are to carry into effect the plan in the event of an environmental emergency and, if the place where one or more substances are located is a place of work, a copy must be available at that place.</Text></Subsection><Subsection><Label>(3)</Label><Text>The person must keep with the plan, a record of the results from the annual updates and tests for a period of not less than five years beginning on the day the record is made.</Text></Subsection><HistoricalNote>SOR/2011-294, s. 5.</HistoricalNote></Section><Section><Label>7</Label><Subsection><Label>(1)</Label><Text>If a person, required to prepare a plan under subsection 4(1), has prepared an environmental emergency plan with respect to one or more of the substances set out in column 1 of Schedule 1 on a voluntary basis or for another government or under another Act of Parliament and the plan meets the requirements of subsections 4(2) and (3), the person may use that plan for the purposes of meeting those requirements.</Text></Subsection><Subsection><Label>(2)</Label><Text>If a person has a plan that is described in subsection (1) except that the plan does not meet all of the requirements of subsections 4(2) and (3), the person may use the plan if they amend the plan so that it meets all of those requirements.</Text></Subsection><Subsection><Label>(3)</Label><Text>If a person amends a plan in accordance with subsection (2), that person must submit to the Minister a report that describes the amended plan and that contains the information requested in Schedule 4 within six months after the day referred to in paragraph 4(4)(b).</Text></Subsection><HistoricalNote>SOR/2011-294, s. 6.</HistoricalNote></Section><Section><Label>8</Label><Text>The notices and reports referred to in subsections 3(1), (4) and (5), 4(4) and 5(1) must be submitted in writing, or in electronic format, if any, that is provided by the Department of the Environment.</Text></Section><Heading level="1"><TitleText>Environmental Emergencies</TitleText></Heading><Section><Label>9</Label><Subsection><Label>(1)</Label><Text>When an environmental emergency occurs in respect of a substance set out in column 1 of Schedule 1, the person who is designated, for the purpose of paragraph 201(1)(a) of the Act, to be provided with a written report is the Regional Director of the Environmental Enforcement Division of the Enforcement Branch of the Department of the Environment in the region where the environmental emergency occurs.</Text></Subsection><Subsection><Label>(2)</Label><Text>The report must include the following information:</Text><Paragraph><Label>(a)</Label><Text>the name, civic address and telephone number of the person who owns or has the charge, management or control of the substance released;</Text></Paragraph><Paragraph><Label>(b)</Label><Text>the date, time and location of the release;</Text></Paragraph><Paragraph><Label>(c)</Label><Text>the name and CAS registry number of the substance released;</Text></Paragraph><Paragraph><Label>(d)</Label><Text>the quantity of the substance released or, if the quantity cannot be determined, an estimate of it;</Text></Paragraph><Paragraph><Label>(e)</Label><Text>the identification of the container from which the substance was released and a description of its condition;</Text></Paragraph><Paragraph><Label>(f)</Label><Text>the location of the release and a description of potential negative effects on the environment or on human life or health;</Text></Paragraph><Paragraph><Label>(g)</Label><Text>a description of the circumstances and of the cause of the release, if known, and of the measures taken to mitigate any negative effects on the environment or on human life or health;</Text></Paragraph><Paragraph><Label>(h)</Label><Text>the identification of all persons and agencies that were notified as a result of the release; and</Text></Paragraph><Paragraph><Label>(i)</Label><Text>all measures taken or planned to be taken to prevent similar releases.</Text></Paragraph></Subsection><HistoricalNote>SOR/2011-294, s. 7.</HistoricalNote></Section><Heading level="1"><TitleText>Coming into Force</TitleText></Heading><Section><Label>10</Label><Text>These Regulations come into force 90 days after the day on which they are registered.</Text></Section></Body><Schedule spanlanguages="no"><ScheduleFormHeading><Label>SCHEDULE 1</Label><OriginatingRef>(Section 2, subsections 3(1), (2) and (5), 4(1) and 7(1))</OriginatingRef><TitleText>List of Substances</TitleText></ScheduleFormHeading><Heading level="1"><Label>PART 1</Label><TitleText>Substances Likely to Explode</TitleText></Heading><TableGroup pointsize="7" topmarginspacing="4"><table frame="topbot"><tgroup cols="4"><colspec colname="1" colwidth="96.23*" /><colspec colname="2" colwidth="193.77*" /><colspec align="left" char="%" charoff="50" colname="4" colwidth="112.75*" /><colspec align="left" char="." charoff="50" colname="5" colwidth="127.94*" /><thead><row topdouble="yes" valign="bottom"><entry char="." colsep="0" rowsep="0" /><entry char="." colsep="0" rowsep="0">Column 1</entry><entry char="." colsep="0" rowsep="0">Column 2</entry><entry colsep="0" rowsep="0">Column 3</entry></row><row valign="bottom"><entry char="." colsep="0" rowsep="1" valign="bottom">CAS Registry Number</entry><entry char="." colsep="0" rowsep="1" valign="bottom">Name of Substance</entry><entry char="." colsep="0" rowsep="1" valign="bottom">Concentration (% by weight)</entry><entry colsep="0" rowsep="1" valign="bottom">Minimum Quantity (metric tonnes)</entry></row></thead><tbody><row valign="bottom"><entry char="." colname="1" colsep="0" rowsep="0" valign="top">60-29-7</entry><entry char="." colname="2" colsep="0" rowsep="0">ethyl ether (diethyl ether)</entry><entry char="." colname="4" colsep="0" rowsep="0">1</entry><entry colname="5" colsep="0" rowsep="0">4.50</entry></row><row valign="bottom"><entry char="." colname="1" colsep="0" rowsep="0" valign="top">71-43-2</entry><entry char="." colname="2" colsep="0" rowsep="0">benzene</entry><entry char="." colname="4" colsep="0" rowsep="0">1</entry><entry colname="5" colsep="0" rowsep="0">10.00</entry></row><row valign="bottom"><entry char="." colname="1" colsep="0" rowsep="0" valign="top">74-82-8</entry><entry char="." colname="2" colsep="0" rowsep="0">methane</entry><entry char="." colname="4" colsep="0" rowsep="0">1</entry><entry colname="5" colsep="0" rowsep="0">4.50</entry></row><row valign="bottom"><entry char="." colname="1" colsep="0" rowsep="0" valign="top">74-84-0</entry><entry char="." colname="2" colsep="0" rowsep="0">ethane</entry><entry char="." colname="4" colsep="0" rowsep="0">1</entry><entry colname="5" colsep="0" rowsep="0">4.50</entry></row><row valign="bottom"><entry char="." colname="1" colsep="0" rowsep="0" valign="top">74-85-1</entry><entry char="." colname="2" colsep="0" rowsep="0">ethylene</entry><entry char="." colname="4" colsep="0" rowsep="0">1</entry><entry colname="5" colsep="0" rowsep="0">4.50</entry></row><row valign="bottom"><entry char="." colname="1" colsep="0" rowsep="0" valign="top">74-86-2</entry><entry char="." colname="2" colsep="0" rowsep="0">acetylene</entry><entry char="." colname="4" colsep="0" rowsep="0">1</entry><entry colname="5" colsep="0" rowsep="0">4.50</entry></row><row valign="bottom"><entry char="." colname="1" colsep="0" rowsep="0" valign="top">74-89-5</entry><entry char="." colname="2" colsep="0" rowsep="0">methylamine</entry><entry char="." colname="4" colsep="0" rowsep="0">1</entry><entry colname="5" colsep="0" rowsep="0">4.50</entry></row><row valign="bottom"><entry char="." colname="1" colsep="0" rowsep="0" valign="top">74-98-6</entry><entry char="." colname="2" colsep="0" rowsep="0">propane</entry><entry char="." colname="4" colsep="0" rowsep="0">1</entry><entry colname="5" colsep="0" rowsep="0">4.50</entry></row><row valign="bottom"><entry char="." colname="1" colsep="0" rowsep="0" valign="top">74-99-7</entry><entry char="." colname="2" colsep="0" rowsep="0">methylacetylene (propyne)</entry><entry char="." colname="4" colsep="0" rowsep="0">1</entry><entry colname="5" colsep="0" rowsep="0">4.50</entry></row><row valign="bottom"><entry char="." colname="1" colsep="0" rowsep="0" valign="top">75-00-3</entry><entry char="." colname="2" colsep="0" rowsep="0">ethyl chloride</entry><entry char="." colname="4" colsep="0" rowsep="0">1</entry><entry colname="5" colsep="0" rowsep="0">4.50</entry></row><row valign="bottom"><entry char="." colname="1" colsep="0" rowsep="0" valign="top">75-01-4</entry><entry char="." colname="2" colsep="0" rowsep="0">vinyl chloride</entry><entry char="." colname="4" colsep="0" rowsep="0">1</entry><entry colname="5" colsep="0" rowsep="0">4.50</entry></row><row valign="bottom"><entry char="." colname="1" colsep="0" rowsep="0" valign="top">75-02-5</entry><entry char="." colname="2" colsep="0" rowsep="0">vinyl fluoride</entry><entry char="." colname="4" colsep="0" rowsep="0">1</entry><entry colname="5" colsep="0" rowsep="0">4.50</entry></row><row valign="bottom"><entry char="." colname="1" colsep="0" rowsep="0" valign="top">75-04-7</entry><entry char="." colname="2" colsep="0" rowsep="0">ethylamine</entry><entry char="." colname="4" colsep="0" rowsep="0">1</entry><entry colname="5" colsep="0" rowsep="0">4.50</entry></row><row valign="bottom"><entry char="." colname="1" colsep="0" rowsep="0" valign="top">75-07-0</entry><entry char="." colname="2" colsep="0" rowsep="0">acetaldehyde</entry><entry char="." colname="4" colsep="0" rowsep="0">1</entry><entry colname="5" colsep="0" rowsep="0">4.50</entry></row><row valign="bottom"><entry char="." colname="1" colsep="0" rowsep="0" valign="top">75-08-1</entry><entry char="." colname="2" colsep="0" rowsep="0">ethyl mercaptan</entry><entry char="." colname="4" colsep="0" rowsep="0">1</entry><entry colname="5" colsep="0" rowsep="0">4.50</entry></row><row valign="bottom"><entry char="." colname="1" colsep="0" rowsep="0" valign="top">75-18-3</entry><entry char="." colname="2" colsep="0" rowsep="0">dimethyl sulphide</entry><entry char="." colname="4" colsep="0" rowsep="0">1</entry><entry colname="5" colsep="0" rowsep="0">150.00</entry></row><row valign="bottom"><entry char="." colname="1" colsep="0" rowsep="0" valign="top">75-19-4</entry><entry char="." colname="2" colsep="0" rowsep="0">cyclopropane</entry><entry char="." colname="4" colsep="0" rowsep="0">1</entry><entry colname="5" colsep="0" rowsep="0">4.50</entry></row><row valign="bottom"><entry char="." colname="1" colsep="0" rowsep="0" valign="top">75-28-5</entry><entry char="." colname="2" colsep="0" rowsep="0">isobutane</entry><entry char="." colname="4" colsep="0" rowsep="0">1</entry><entry colname="5" colsep="0" rowsep="0">4.50</entry></row><row valign="bottom"><entry char="." colname="1" colsep="0" rowsep="0" valign="top">75-29-6</entry><entry char="." colname="2" colsep="0" rowsep="0">2-chloropropane (isopropyl chloride)</entry><entry char="." colname="4" colsep="0" rowsep="0">1</entry><entry colname="5" colsep="0" rowsep="0">4.50</entry></row><row valign="bottom"><entry char="." colname="1" colsep="0" rowsep="0" valign="top">75-31-0</entry><entry char="." colname="2" colsep="0" rowsep="0">isopropylamine</entry><entry char="." colname="4" colsep="0" rowsep="0">1</entry><entry colname="5" colsep="0" rowsep="0">4.50</entry></row><row valign="bottom"><entry char="." colname="1" colsep="0" rowsep="0" valign="top">75-35-4</entry><entry char="." colname="2" colsep="0" rowsep="0">vinylidene chloride</entry><entry char="." colname="4" colsep="0" rowsep="0">1</entry><entry colname="5" colsep="0" rowsep="0">4.50</entry></row><row valign="bottom"><entry char="." colname="1" colsep="0" rowsep="0" valign="top">75-37-6</entry><entry char="." colname="2" colsep="0" rowsep="0">difluoroethane (1,1-difluoroethane)</entry><entry char="." colname="4" colsep="0" rowsep="0">1</entry><entry colname="5" colsep="0" rowsep="0">4.50</entry></row><row valign="bottom"><entry char="." colname="1" colsep="0" rowsep="0" valign="top">75-38-7</entry><entry char="." colname="2" colsep="0" rowsep="0">1,1-difluoroethylene (vinylidene fluoride)</entry><entry char="." colname="4" colsep="0" rowsep="0">1</entry><entry colname="5" colsep="0" rowsep="0">4.50</entry></row><row valign="bottom"><entry char="." colname="1" colsep="0" rowsep="0" valign="top">75-50-3</entry><entry char="." colname="2" colsep="0" rowsep="0">trimethylamine</entry><entry char="." colname="4" colsep="0" rowsep="0">1</entry><entry colname="5" colsep="0" rowsep="0">4.50</entry></row><row valign="bottom"><entry char="." colname="1" colsep="0" rowsep="0" valign="top">75-64-9</entry><entry char="." colname="2" colsep="0" rowsep="0"><Emphasis style="italic">tert</Emphasis>-butylamine (2-amino-2-methylpropane)</entry><entry char="." colname="4" colsep="0" rowsep="0">1</entry><entry colname="5" colsep="0" rowsep="0">150.00</entry></row><row valign="bottom"><entry char="." colname="1" colsep="0" rowsep="0" valign="top">75-76-3</entry><entry char="." colname="2" colsep="0" rowsep="0">tetramethylsilane</entry><entry char="." colname="4" colsep="0" rowsep="0">1</entry><entry colname="5" colsep="0" rowsep="0">4.50</entry></row><row valign="bottom"><entry char="." colname="1" colsep="0" rowsep="0" valign="top">78-78-4</entry><entry char="." colname="2" colsep="0" rowsep="0">isopentane (2-methylbutane)</entry><entry char="." colname="4" colsep="0" rowsep="0">1</entry><entry colname="5" colsep="0" rowsep="0">4.50</entry></row><row valign="bottom"><entry char="." colname="1" colsep="0" rowsep="0" valign="top">78-79-5</entry><entry char="." colname="2" colsep="0" rowsep="0">isoprene</entry><entry char="." colname="4" colsep="0" rowsep="0">1</entry><entry colname="5" colsep="0" rowsep="0">4.50</entry></row><row valign="bottom"><entry char="." colname="1" colsep="0" rowsep="0" valign="top">79-38-9</entry><entry char="." colname="2" colsep="0" rowsep="0">trifluorochloroethylene (chlorotrifluoroethylene)</entry><entry char="." colname="4" colsep="0" rowsep="0">1</entry><entry colname="5" colsep="0" rowsep="0">4.50</entry></row><row valign="bottom"><entry char="." colname="1" colsep="0" rowsep="0" valign="top">100-41-4</entry><entry char="." colname="2" colsep="0" rowsep="0">ethylbenzene</entry><entry char="." colname="4" colsep="0" rowsep="0">1</entry><entry colname="5" colsep="0" rowsep="0">7000.00</entry></row><row valign="bottom"><entry char="." colname="1" colsep="0" rowsep="0" valign="top">100-42-5</entry><entry char="." colname="2" colsep="0" rowsep="0">styrene</entry><entry char="." colname="4" colsep="0" rowsep="0">10</entry><entry colname="5" colsep="0" rowsep="0">4.50</entry></row><row valign="bottom"><entry char="." colname="1" colsep="0" rowsep="0" valign="top">106-97-8</entry><entry char="." colname="2" colsep="0" rowsep="0">butane</entry><entry char="." colname="4" colsep="0" rowsep="0">1</entry><entry colname="5" colsep="0" rowsep="0">4.50</entry></row><row valign="bottom"><entry char="." colname="1" colsep="0" rowsep="0" valign="top">106-98-9</entry><entry char="." colname="2" colsep="0" rowsep="0">1-butene (alpha-butylene)</entry><entry char="." colname="4" colsep="0" rowsep="0">1</entry><entry colname="5" colsep="0" rowsep="0">4.50</entry></row><row valign="bottom"><entry char="." colname="1" colsep="0" rowsep="0" valign="top">106-99-0</entry><entry char="." colname="2" colsep="0" rowsep="0">1,3-butadiene</entry><entry char="." colname="4" colsep="0" rowsep="0">1</entry><entry colname="5" colsep="0" rowsep="0">4.50</entry></row><row valign="bottom"><entry char="." colname="1" colsep="0" rowsep="0" valign="top">107-00-6</entry><entry char="." colname="2" colsep="0" rowsep="0">ethylacetylene</entry><entry char="." colname="4" colsep="0" rowsep="0">1</entry><entry colname="5" colsep="0" rowsep="0">4.50</entry></row><row valign="bottom"><entry char="." colname="1" colsep="0" rowsep="0" valign="top">107-01-7</entry><entry char="." colname="2" colsep="0" rowsep="0">2-butene</entry><entry char="." colname="4" colsep="0" rowsep="0">1</entry><entry colname="5" colsep="0" rowsep="0">4.50</entry></row><row valign="bottom"><entry char="." colname="1" colsep="0" rowsep="0" valign="top">107-25-5</entry><entry char="." colname="2" colsep="0" rowsep="0">vinyl methyl ether</entry><entry char="." colname="4" colsep="0" rowsep="0">1</entry><entry colname="5" colsep="0" rowsep="0">4.50</entry></row><row valign="bottom"><entry char="." colname="1" colsep="0" rowsep="0" valign="top">107-31-3</entry><entry char="." colname="2" colsep="0" rowsep="0">methyl formate</entry><entry char="." colname="4" colsep="0" rowsep="0">1</entry><entry colname="5" colsep="0" rowsep="0">4.50</entry></row><row valign="bottom"><entry char="." colname="1" colsep="0" rowsep="0" valign="top">108-88-3</entry><entry char="." colname="2" colsep="0" rowsep="0">toluene</entry><entry char="." colname="4" colsep="0" rowsep="0">1</entry><entry colname="5" colsep="0" rowsep="0">2500.00</entry></row><row valign="bottom"><entry char="." colname="1" colsep="0" rowsep="0" valign="top">109-66-0</entry><entry char="." colname="2" colsep="0" rowsep="0">n-pentane (pentane)</entry><entry char="." colname="4" colsep="0" rowsep="0">1</entry><entry colname="5" colsep="0" rowsep="0">4.50</entry></row><row valign="bottom"><entry char="." colname="1" colsep="0" rowsep="0" valign="top">109-67-1</entry><entry char="." colname="2" colsep="0" rowsep="0">1-pentene</entry><entry char="." colname="4" colsep="0" rowsep="0">1</entry><entry colname="5" colsep="0" rowsep="0">4.50</entry></row><row valign="bottom"><entry char="." colname="1" colsep="0" rowsep="0" valign="top">109-92-2</entry><entry char="." colname="2" colsep="0" rowsep="0">vinyl ethyl ether (ethyl vinyl ether)</entry><entry char="." colname="4" colsep="0" rowsep="0">1</entry><entry colname="5" colsep="0" rowsep="0">4.50</entry></row><row valign="bottom"><entry char="." colname="1" colsep="0" rowsep="0" valign="top">109-95-5</entry><entry char="." colname="2" colsep="0" rowsep="0">ethyl nitrite</entry><entry char="." colname="4" colsep="0" rowsep="0">1</entry><entry colname="5" colsep="0" rowsep="0">4.50</entry></row><row valign="bottom"><entry char="." colname="1" colsep="0" rowsep="0" valign="top">110-82-7</entry><entry char="." colname="2" colsep="0" rowsep="0">cyclohexane</entry><entry char="." colname="4" colsep="0" rowsep="0">1</entry><entry colname="5" colsep="0" rowsep="0">550.00</entry></row><row valign="bottom"><entry char="." colname="1" colsep="0" rowsep="0" valign="top">115-07-1</entry><entry char="." colname="2" colsep="0" rowsep="0">propylene</entry><entry char="." colname="4" colsep="0" rowsep="0">1</entry><entry colname="5" colsep="0" rowsep="0">4.50</entry></row><row valign="bottom"><entry char="." colname="1" colsep="0" rowsep="0" valign="top">115-10-6</entry><entry char="." colname="2" colsep="0" rowsep="0">dimethyl ether (methyl ether)</entry><entry char="." colname="4" colsep="0" rowsep="0">1</entry><entry colname="5" colsep="0" rowsep="0">4.50</entry></row><row valign="bottom"><entry char="." colname="1" colsep="0" rowsep="0" valign="top">115-11-7</entry><entry char="." colname="2" colsep="0" rowsep="0">isobutylene (2-methylpropene)</entry><entry char="." colname="4" colsep="0" rowsep="0">1</entry><entry colname="5" colsep="0" rowsep="0">4.50</entry></row><row valign="bottom"><entry char="." colname="1" colsep="0" rowsep="0" valign="top">116-14-3</entry><entry char="." colname="2" colsep="0" rowsep="0">tetrafluoroethylene</entry><entry char="." colname="4" colsep="0" rowsep="0">1</entry><entry colname="5" colsep="0" rowsep="0">4.50</entry></row><row valign="bottom"><entry char="." colname="1" colsep="0" rowsep="0" valign="top">124-40-3</entry><entry char="." colname="2" colsep="0" rowsep="0">dimethylamine</entry><entry char="." colname="4" colsep="0" rowsep="0">1</entry><entry colname="5" colsep="0" rowsep="0">4.50</entry></row><row valign="bottom"><entry char="." colname="1" colsep="0" rowsep="0" valign="top">460-19-5</entry><entry char="." colname="2" colsep="0" rowsep="0">cyanogen</entry><entry char="." colname="4" colsep="0" rowsep="0">1</entry><entry colname="5" colsep="0" rowsep="0">4.50</entry></row><row valign="bottom"><entry char="." colname="1" colsep="0" rowsep="0" valign="top">463-49-0</entry><entry char="." colname="2" colsep="0" rowsep="0">propadiene</entry><entry char="." colname="4" colsep="0" rowsep="0">1</entry><entry colname="5" colsep="0" rowsep="0">4.50</entry></row><row valign="bottom"><entry char="." colname="1" colsep="0" rowsep="0" valign="top">463-58-1</entry><entry char="." colname="2" colsep="0" rowsep="0">carbonyl sulphide (carbon oxysulfide)</entry><entry char="." colname="4" colsep="0" rowsep="0">1</entry><entry colname="5" colsep="0" rowsep="0">4.50</entry></row><row valign="bottom"><entry char="." colname="1" colsep="0" rowsep="0" valign="top">463-82-1</entry><entry char="." colname="2" colsep="0" rowsep="0">2,2-dimethylpropane</entry><entry char="." colname="4" colsep="0" rowsep="0">1</entry><entry colname="5" colsep="0" rowsep="0">4.50</entry></row><row valign="bottom"><entry char="." colname="1" colsep="0" rowsep="0" valign="top">504-60-9</entry><entry char="." colname="2" colsep="0" rowsep="0">1,3-pentadiene</entry><entry char="." colname="4" colsep="0" rowsep="0">1</entry><entry colname="5" colsep="0" rowsep="0">4.50</entry></row><row valign="bottom"><entry char="." colname="1" colsep="0" rowsep="0" valign="top">557-98-2</entry><entry char="." colname="2" colsep="0" rowsep="0">2-chloropropene (2-chloropropylene)</entry><entry char="." colname="4" colsep="0" rowsep="0">1</entry><entry colname="5" colsep="0" rowsep="0">4.50</entry></row><row valign="bottom"><entry char="." colname="1" colsep="0" rowsep="0" valign="top">563-45-1</entry><entry char="." colname="2" colsep="0" rowsep="0">3-methyl-1-butene</entry><entry char="." colname="4" colsep="0" rowsep="0">1</entry><entry colname="5" colsep="0" rowsep="0">4.50</entry></row><row valign="bottom"><entry char="." colname="1" colsep="0" rowsep="0" valign="top">563-46-2</entry><entry char="." colname="2" colsep="0" rowsep="0">2-methyl-1-butene</entry><entry char="." colname="4" colsep="0" rowsep="0">1</entry><entry colname="5" colsep="0" rowsep="0">4.50</entry></row><row valign="bottom"><entry char="." colname="1" colsep="0" rowsep="0" valign="top">590-18-1</entry><entry char="." colname="2" colsep="0" rowsep="0"><Emphasis style="italic">cis</Emphasis>-2-butene (2-butene-<Emphasis style="italic">cis</Emphasis>)</entry><entry char="." colname="4" colsep="0" rowsep="0">1</entry><entry colname="5" colsep="0" rowsep="0">4.50</entry></row><row valign="bottom"><entry char="." colname="1" colsep="0" rowsep="0" valign="top">590-21-6</entry><entry char="." colname="2" colsep="0" rowsep="0">1-chloropropene (1-chloropropylene)</entry><entry char="." colname="4" colsep="0" rowsep="0">1</entry><entry colname="5" colsep="0" rowsep="0">4.50</entry></row><row valign="bottom"><entry char="." colname="1" colsep="0" rowsep="0" valign="top">598-73-2</entry><entry char="." colname="2" colsep="0" rowsep="0">bromotrifluoroethylene</entry><entry char="." colname="4" colsep="0" rowsep="0">1</entry><entry colname="5" colsep="0" rowsep="0">4.50</entry></row><row valign="bottom"><entry char="." colname="1" colsep="0" rowsep="0" valign="top">624-64-6</entry><entry char="." colname="2" colsep="0" rowsep="0"><Emphasis style="italic">trans</Emphasis>-2-butene (2-butene-<Emphasis style="italic">trans</Emphasis>)</entry><entry char="." colname="4" colsep="0" rowsep="0">1</entry><entry colname="5" colsep="0" rowsep="0">4.50</entry></row><row valign="bottom"><entry char="." colname="1" colsep="0" rowsep="0" valign="top">627-20-3</entry><entry char="." colname="2" colsep="0" rowsep="0"><Emphasis style="italic">cis</Emphasis>-2-pentene (beta-<Emphasis style="italic">cis</Emphasis>-amylene)</entry><entry char="." colname="4" colsep="0" rowsep="0">1</entry><entry colname="5" colsep="0" rowsep="0">4.50</entry></row><row valign="bottom"><entry char="." colname="1" colsep="0" rowsep="0" valign="top">646-04-8</entry><entry char="." colname="2" colsep="0" rowsep="0"><Emphasis style="italic">trans</Emphasis>-2-pentene (<Emphasis style="italic">trans</Emphasis>-beta-amylene)</entry><entry char="." colname="4" colsep="0" rowsep="0">1</entry><entry colname="5" colsep="0" rowsep="0">4.50</entry></row><row valign="bottom"><entry char="." colname="1" colsep="0" rowsep="0" valign="top">689-97-4</entry><entry char="." colname="2" colsep="0" rowsep="0">1-buten-3-yne (vinyl acetylene)</entry><entry char="." colname="4" colsep="0" rowsep="0">1</entry><entry colname="5" colsep="0" rowsep="0">4.50</entry></row><row valign="bottom"><entry char="." colname="1" colsep="0" rowsep="0" valign="top">1330-20-7</entry><entry char="." colname="2" colsep="0" rowsep="0">xylenes</entry><entry char="." colname="4" colsep="0" rowsep="0">1</entry><entry colname="5" colsep="0" rowsep="0">8000.00</entry></row><row valign="bottom"><entry char="." colname="1" colsep="0" rowsep="0" valign="top">1333-74-0</entry><entry char="." colname="2" colsep="0" rowsep="0">hydrogen</entry><entry char="." colname="4" colsep="0" rowsep="0">1</entry><entry colname="5" colsep="0" rowsep="0">4.50</entry></row><row valign="bottom"><entry char="." colname="1" colsep="0" rowsep="0" valign="top">4109-96-0</entry><entry char="." colname="2" colsep="0" rowsep="0">dichlorosilane</entry><entry char="." colname="4" colsep="0" rowsep="0">1</entry><entry colname="5" colsep="0" rowsep="0">4.50</entry></row><row valign="bottom"><entry char="." colsep="0" rowsep="0" valign="top">6484-52-2</entry><entry char="." colsep="0" rowsep="0">ammonium nitrate (in solid form)</entry><entry char="." colname="4" colsep="0" rowsep="0">60</entry><entry colname="5" colsep="0" rowsep="0">20.00</entry></row><row valign="bottom"><entry char="." colsep="0" rowsep="0" valign="top">6484-52-2</entry><entry char="." colsep="0" rowsep="0">ammonium nitrate (in liquid form)</entry><entry char="." colname="4" colsep="0" rowsep="0">81</entry><entry colname="5" colsep="0" rowsep="0">20.00</entry></row><row valign="bottom"><entry char="." colname="1" colsep="0" rowsep="0" valign="top">7722-84-1</entry><entry char="." colname="2" colsep="0" rowsep="0">hydrogen peroxide</entry><entry char="." colname="4" colsep="0" rowsep="0">52</entry><entry colname="5" colsep="0" rowsep="0">3.40</entry></row><row valign="bottom"><entry char="." colname="1" colsep="0" rowsep="0" valign="top">7775-09-9</entry><entry char="." colname="2" colsep="0" rowsep="0">sodium chlorate</entry><entry char="." colname="4" colsep="0" rowsep="0">10</entry><entry colname="5" colsep="0" rowsep="0">10.00</entry></row><row valign="bottom"><entry char="." colname="1" colsep="0" rowsep="0" valign="top">7790-98-9</entry><entry char="." colname="2" colsep="0" rowsep="0">ammonium perchlorate</entry><entry char="." colname="4" colsep="0" rowsep="0">1</entry><entry colname="5" colsep="0" rowsep="0">3.40</entry></row><row valign="bottom"><entry char="." colname="1" colsep="0" rowsep="0" valign="top">7791-21-1</entry><entry char="." colname="2" colsep="0" rowsep="0">chlorine monoxide (dichlorine oxide)</entry><entry char="." colname="4" colsep="0" rowsep="0">1</entry><entry colname="5" colsep="0" rowsep="0">4.50</entry></row><row valign="bottom"><entry char="." colname="1" colsep="0" rowsep="0" valign="top">7803-62-5</entry><entry char="." colname="2" colsep="0" rowsep="0">silane</entry><entry char="." colname="4" colsep="0" rowsep="0">1</entry><entry colname="5" colsep="0" rowsep="0">4.50</entry></row><row valign="bottom"><entry char="." colname="1" colsep="0" rowsep="0" valign="top">8006-14-2</entry><entry char="." colname="2" colsep="0" rowsep="0">liquefied natural gas</entry><entry char="." colname="4" colsep="0" rowsep="0">1</entry><entry colname="5" colsep="0" rowsep="0">4.50</entry></row><row valign="bottom"><entry char="." colsep="0" rowsep="0" valign="top">8006-61-9</entry><entry char="." colsep="0" rowsep="0">gasoline (unleaded)</entry><entry char="." colname="4" colsep="0" rowsep="0">1</entry><entry colname="5" colsep="0" rowsep="0">150.00</entry></row><row valign="bottom"><entry char="." colname="1" colsep="0" rowsep="0" valign="top">8030-30-6</entry><entry char="." colname="2" colsep="0" rowsep="0">naphtha</entry><entry char="." colname="4" colsep="0" rowsep="0">1</entry><entry colname="5" colsep="0" rowsep="0">50.00</entry></row><row valign="bottom"><entry char="." colname="1" colsep="0" rowsep="0" valign="top">10025-78-2</entry><entry char="." colname="2" colsep="0" rowsep="0">trichlorosilane</entry><entry char="." colname="4" colsep="0" rowsep="0">1</entry><entry colname="5" colsep="0" rowsep="0">4.50</entry></row><row valign="bottom"><entry char="." colname="1" colsep="0" rowsep="0" valign="top">25167-67-3</entry><entry char="." colname="2" colsep="0" rowsep="0">butylene (butene)</entry><entry char="." colname="4" colsep="0" rowsep="0">1</entry><entry colname="5" colsep="0" rowsep="0">4.50</entry></row><row valign="bottom"><entry char="." colname="1" colsep="0" rowsep="0" valign="top">86290-81-5</entry><entry char="." colname="2" colsep="0" rowsep="0">gasoline (motor fuel)</entry><entry char="." colname="4" colsep="0" rowsep="0">1</entry><entry colname="5" colsep="0" rowsep="0">150.00</entry></row></tbody></tgroup></table></TableGroup><Heading level="1"><Label>PART 2</Label><TitleText>Substances Hazardous When Inhaled</TitleText></Heading><TableGroup pointsize="7" topmarginspacing="4"><table frame="topbot"><tgroup cols="4"><colspec char="." colname="1" colwidth="97.33*" /><colspec char="." colname="2" colwidth="194.22*" /><colspec align="left" char="." charoff="50" colname="4" colwidth="113.17*" /><colspec align="left" char="." charoff="50" colname="5" colwidth="127.81*" /><thead><row topdouble="yes"><entry colsep="0" rowsep="0" valign="top" /><entry colsep="0" rowsep="0">Column 1</entry><entry colsep="0" rowsep="0">Column 2</entry><entry colsep="0" rowsep="0">Column 3</entry></row><row valign="bottom"><entry colsep="0" rowsep="1" valign="bottom">CAS Registry Number</entry><entry colsep="0" rowsep="1" valign="bottom">Name of Substance</entry><entry colsep="0" rowsep="1" valign="bottom">Concentration (% by weight)</entry><entry colsep="0" rowsep="1" valign="bottom">Minimum Quantity (metric tonnes)</entry></row></thead><tbody><row valign="bottom"><entry colname="1" colsep="0" rowsep="0" valign="top">50-00-0</entry><entry colname="2" colsep="0" rowsep="0">formaldehyde, solution</entry><entry colname="4" colsep="0" rowsep="0">10</entry><entry colname="5" colsep="0" rowsep="0">6.80</entry></row><row valign="bottom"><entry colname="1" colsep="0" rowsep="0" valign="top">57-14-7</entry><entry colname="2" colsep="0" rowsep="0">1,1-dimethylhydrazine</entry><entry colname="4" colsep="0" rowsep="0">10</entry><entry colname="5" colsep="0" rowsep="0">6.80</entry></row><row valign="bottom"><entry colname="1" colsep="0" rowsep="0" valign="top">60-34-4</entry><entry colname="2" colsep="0" rowsep="0">methylhydrazine (monomethyl hydrazine)</entry><entry colname="4" colsep="0" rowsep="0">10</entry><entry colname="5" colsep="0" rowsep="0">6.80</entry></row><row valign="bottom"><entry colsep="0" rowsep="0" valign="top">64-19-7</entry><entry colname="2" colsep="0" rowsep="0">acetic acid</entry><entry colname="4" colsep="0" rowsep="0">95</entry><entry colname="5" colsep="0" rowsep="0">6.80</entry></row><row valign="bottom"><entry colname="1" colsep="0" rowsep="0" valign="top">67-66-3</entry><entry colname="2" colsep="0" rowsep="0">chloroform (trichloromethane)</entry><entry colname="4" colsep="0" rowsep="0">10</entry><entry colname="5" colsep="0" rowsep="0">9.10</entry></row><row valign="bottom"><entry colname="1" colsep="0" rowsep="0" valign="top">74-83-9</entry><entry colname="2" colsep="0" rowsep="0">methyl bromide</entry><entry colname="4" colsep="0" rowsep="0">10</entry><entry colname="5" colsep="0" rowsep="0">2.27</entry></row><row valign="bottom"><entry colname="1" colsep="0" rowsep="0" valign="top">74-87-3</entry><entry colname="2" colsep="0" rowsep="0">methyl chloride</entry><entry colname="4" colsep="0" rowsep="0">10</entry><entry colname="5" colsep="0" rowsep="0">4.50</entry></row><row valign="bottom"><entry colname="1" colsep="0" rowsep="0" valign="top">74-88-4</entry><entry colname="2" colsep="0" rowsep="0">methyl iodide</entry><entry colname="4" colsep="0" rowsep="0">10</entry><entry colname="5" colsep="0" rowsep="0">4.50</entry></row><row valign="bottom"><entry colname="1" colsep="0" rowsep="0" valign="top">74-90-8</entry><entry colname="2" colsep="0" rowsep="0">hydrogen cyanide (hydrocyanic acid)</entry><entry colname="4" colsep="0" rowsep="0">10</entry><entry colname="5" colsep="0" rowsep="0">1.13</entry></row><row valign="bottom"><entry colname="1" colsep="0" rowsep="0" valign="top">74-93-1</entry><entry colname="2" colsep="0" rowsep="0">methyl mercaptan</entry><entry colname="4" colsep="0" rowsep="0">10</entry><entry colname="5" colsep="0" rowsep="0">4.50</entry></row><row valign="bottom"><entry colsep="0" rowsep="0" valign="top">75-09-2</entry><entry colsep="0" rowsep="0">dichloromethane (methylene chloride)</entry><entry colname="4" colsep="0" rowsep="0">1</entry><entry colname="5" colsep="0" rowsep="0">9.10</entry></row><row valign="bottom"><entry colname="1" colsep="0" rowsep="0" valign="top">75-15-0</entry><entry colname="2" colsep="0" rowsep="0">carbon disulphide</entry><entry colname="4" colsep="0" rowsep="0">10</entry><entry colname="5" colsep="0" rowsep="0">9.10</entry></row><row valign="bottom"><entry colname="1" colsep="0" rowsep="0" valign="top">75-21-8</entry><entry colname="2" colsep="0" rowsep="0">ethylene oxide</entry><entry colname="4" colsep="0" rowsep="0">10</entry><entry colname="5" colsep="0" rowsep="0">4.50</entry></row><row valign="bottom"><entry colname="1" colsep="0" rowsep="0" valign="top">75-44-5</entry><entry colname="2" colsep="0" rowsep="0">phosgene</entry><entry colname="4" colsep="0" rowsep="0">1</entry><entry colname="5" colsep="0" rowsep="0">0.22</entry></row><row valign="bottom"><entry colname="1" colsep="0" rowsep="0" valign="top">75-55-8</entry><entry colname="2" colsep="0" rowsep="0">propyleneimine</entry><entry colname="4" colsep="0" rowsep="0">10</entry><entry colname="5" colsep="0" rowsep="0">4.50</entry></row><row valign="bottom"><entry colname="1" colsep="0" rowsep="0" valign="top">75-56-9</entry><entry colname="2" colsep="0" rowsep="0">propylene oxide</entry><entry colname="4" colsep="0" rowsep="0">10</entry><entry colname="5" colsep="0" rowsep="0">4.50</entry></row><row valign="bottom"><entry colname="1" colsep="0" rowsep="0" valign="top">75-74-1</entry><entry colname="2" colsep="0" rowsep="0">tetramethyl lead</entry><entry colname="4" colsep="0" rowsep="0">10</entry><entry colname="5" colsep="0" rowsep="0">4.50</entry></row><row valign="bottom"><entry colname="1" colsep="0" rowsep="0" valign="top">75-77-4</entry><entry colname="2" colsep="0" rowsep="0">trimethylchlorosilane (chlorotrimethylsilane)</entry><entry colname="4" colsep="0" rowsep="0">10</entry><entry colname="5" colsep="0" rowsep="0">4.50</entry></row><row valign="bottom"><entry colname="1" colsep="0" rowsep="0" valign="top">75-78-5</entry><entry colname="2" colsep="0" rowsep="0">dimethyldichlorosilane (dichlorodimethylsilane)</entry><entry colname="4" colsep="0" rowsep="0">10</entry><entry colname="5" colsep="0" rowsep="0">2.27</entry></row><row valign="bottom"><entry colname="1" colsep="0" rowsep="0" valign="top">75-79-6</entry><entry colname="2" colsep="0" rowsep="0">methyltrichlorosilane</entry><entry colname="4" colsep="0" rowsep="0">10</entry><entry colname="5" colsep="0" rowsep="0">2.27</entry></row><row valign="bottom"><entry colname="1" colsep="0" rowsep="0" valign="top">76-06-2</entry><entry colname="2" colsep="0" rowsep="0">chloropicrin (trichloronitromethane)</entry><entry colname="4" colsep="0" rowsep="0">10</entry><entry colname="5" colsep="0" rowsep="0">2.27</entry></row><row valign="bottom"><entry colname="1" colsep="0" rowsep="0" valign="top">78-00-2</entry><entry colname="2" colsep="0" rowsep="0">tetraethyl lead</entry><entry colname="4" colsep="0" rowsep="0">10</entry><entry colname="5" colsep="0" rowsep="0">2.27</entry></row><row valign="bottom"><entry colname="1" colsep="0" rowsep="0" valign="top">78-82-0</entry><entry colname="2" colsep="0" rowsep="0">isobutyronitrile</entry><entry colname="4" colsep="0" rowsep="0">10</entry><entry colname="5" colsep="0" rowsep="0">9.10</entry></row><row valign="bottom"><entry colname="1" colsep="0" rowsep="0" valign="top">79-21-0</entry><entry colname="2" colsep="0" rowsep="0">peroxyacetic acid (peracetic acid)</entry><entry colname="4" colsep="0" rowsep="0">10</entry><entry colname="5" colsep="0" rowsep="0">4.50</entry></row><row valign="bottom"><entry colname="1" colsep="0" rowsep="0" valign="top">79-22-1</entry><entry colname="2" colsep="0" rowsep="0">methyl chloroformate</entry><entry colname="4" colsep="0" rowsep="0">10</entry><entry colname="5" colsep="0" rowsep="0">2.27</entry></row><row valign="bottom"><entry colname="1" colsep="0" rowsep="0" valign="top">91-08-7</entry><entry colname="2" colsep="0" rowsep="0">toluene-2,6-diisocyanate</entry><entry colname="4" colsep="0" rowsep="0">10</entry><entry colname="5" colsep="0" rowsep="0">4.50</entry></row><row valign="bottom"><entry colname="1" colsep="0" rowsep="0" valign="top">106-89-8</entry><entry colname="2" colsep="0" rowsep="0">epichlorohydrin</entry><entry colname="4" colsep="0" rowsep="0">10</entry><entry colname="5" colsep="0" rowsep="0">9.10</entry></row><row valign="bottom"><entry colname="1" colsep="0" rowsep="0" valign="top">107-02-8</entry><entry colname="2" colsep="0" rowsep="0">acrolein</entry><entry colname="4" colsep="0" rowsep="0">10</entry><entry colname="5" colsep="0" rowsep="0">2.27</entry></row><row valign="bottom"><entry colname="1" colsep="0" rowsep="0" valign="top">107-05-1</entry><entry colname="2" colsep="0" rowsep="0">allyl chloride</entry><entry colname="4" colsep="0" rowsep="0">10</entry><entry colname="5" colsep="0" rowsep="0">9.10</entry></row><row valign="bottom"><entry colname="1" colsep="0" rowsep="0" valign="top">107-06-2</entry><entry colname="2" colsep="0" rowsep="0">ethylene dichloride (1,2-dichloroethane)</entry><entry colname="4" colsep="0" rowsep="0">10</entry><entry colname="5" colsep="0" rowsep="0">6.80</entry></row><row valign="bottom"><entry colname="1" colsep="0" rowsep="0" valign="top">107-07-3</entry><entry colname="2" colsep="0" rowsep="0">ethylene chlorohydrin (2-chloroethanol)</entry><entry colname="4" colsep="0" rowsep="0">10</entry><entry colname="5" colsep="0" rowsep="0">4.50</entry></row><row valign="bottom"><entry colname="1" colsep="0" rowsep="0" valign="top">107-11-9</entry><entry colname="2" colsep="0" rowsep="0">allylamine</entry><entry colname="4" colsep="0" rowsep="0">10</entry><entry colname="5" colsep="0" rowsep="0">4.50</entry></row><row valign="bottom"><entry colname="1" colsep="0" rowsep="0" valign="top">107-12-0</entry><entry colname="2" colsep="0" rowsep="0">propionitrile</entry><entry colname="4" colsep="0" rowsep="0">10</entry><entry colname="5" colsep="0" rowsep="0">4.50</entry></row><row valign="bottom"><entry colname="1" colsep="0" rowsep="0" valign="top">107-13-1</entry><entry colname="2" colsep="0" rowsep="0">acrylonitrile</entry><entry colname="4" colsep="0" rowsep="0">10</entry><entry colname="5" colsep="0" rowsep="0">9.10</entry></row><row valign="bottom"><entry colname="1" colsep="0" rowsep="0" valign="top">107-15-3</entry><entry colname="2" colsep="0" rowsep="0">ethylenediamine</entry><entry colname="4" colsep="0" rowsep="0">10</entry><entry colname="5" colsep="0" rowsep="0">9.10</entry></row><row valign="bottom"><entry colname="1" colsep="0" rowsep="0" valign="top">107-18-6</entry><entry colname="2" colsep="0" rowsep="0">allyl alcohol</entry><entry colname="4" colsep="0" rowsep="0">10</entry><entry colname="5" colsep="0" rowsep="0">6.80</entry></row><row valign="bottom"><entry colname="1" colsep="0" rowsep="0" valign="top">107-30-2</entry><entry colname="2" colsep="0" rowsep="0">methyl chloromethyl ether (chloromethyl methyl ether)</entry><entry colname="4" colsep="0" rowsep="0">10</entry><entry colname="5" colsep="0" rowsep="0">2.27</entry></row><row valign="bottom"><entry colname="1" colsep="0" rowsep="0" valign="top">108-05-4</entry><entry colname="2" colsep="0" rowsep="0">vinyl acetate</entry><entry colname="4" colsep="0" rowsep="0">10</entry><entry colname="5" colsep="0" rowsep="0">6.80</entry></row><row valign="bottom"><entry colname="1" colsep="0" rowsep="0" valign="top">108-23-6</entry><entry colname="2" colsep="0" rowsep="0">isopropyl chloroformate</entry><entry colname="4" colsep="0" rowsep="0">10</entry><entry colname="5" colsep="0" rowsep="0">6.80</entry></row><row valign="bottom"><entry colname="1" colsep="0" rowsep="0" valign="top">108-91-8</entry><entry colname="2" colsep="0" rowsep="0">cyclohexylamine</entry><entry colname="4" colsep="0" rowsep="0">10</entry><entry colname="5" colsep="0" rowsep="0">6.80</entry></row><row valign="bottom"><entry colname="1" colsep="0" rowsep="0" valign="top">108-95-2</entry><entry colname="2" colsep="0" rowsep="0">phenol</entry><entry colname="4" colsep="0" rowsep="0">10</entry><entry colname="5" colsep="0" rowsep="0">9.10</entry></row><row valign="bottom"><entry colname="1" colsep="0" rowsep="0" valign="top">109-61-5</entry><entry colname="2" colsep="0" rowsep="0">n-propyl chloroformate (propyl chloroformate)</entry><entry colname="4" colsep="0" rowsep="0">10</entry><entry colname="5" colsep="0" rowsep="0">6.80</entry></row><row valign="bottom"><entry colname="1" colsep="0" rowsep="0" valign="top">110-00-9</entry><entry colname="2" colsep="0" rowsep="0">furan</entry><entry colname="4" colsep="0" rowsep="0">10</entry><entry colname="5" colsep="0" rowsep="0">2.27</entry></row><row valign="bottom"><entry colname="1" colsep="0" rowsep="0" valign="top">110-89-4</entry><entry colname="2" colsep="0" rowsep="0">piperidine</entry><entry colname="4" colsep="0" rowsep="0">10</entry><entry colname="5" colsep="0" rowsep="0">6.80</entry></row><row valign="bottom"><entry colname="1" colsep="0" rowsep="0" valign="top">123-73-9</entry><entry colname="2" colsep="0" rowsep="0"><Emphasis style="italic">trans</Emphasis>-crotonaldehyde</entry><entry colname="4" colsep="0" rowsep="0">10</entry><entry colname="5" colsep="0" rowsep="0">9.10</entry></row><row valign="bottom"><entry colname="1" colsep="0" rowsep="0" valign="top">126-98-7</entry><entry colname="2" colsep="0" rowsep="0">methylacrylonitrile</entry><entry colname="4" colsep="0" rowsep="0">10</entry><entry colname="5" colsep="0" rowsep="0">4.50</entry></row><row valign="bottom"><entry colname="1" colsep="0" rowsep="0" valign="top">151-56-4</entry><entry colname="2" colsep="0" rowsep="0">ethyleneimine</entry><entry colname="4" colsep="0" rowsep="0">10</entry><entry colname="5" colsep="0" rowsep="0">4.50</entry></row><row valign="bottom"><entry colname="1" colsep="0" rowsep="0" valign="top">302-01-2</entry><entry colname="2" colsep="0" rowsep="0">hydrazine</entry><entry colname="4" colsep="0" rowsep="0">10</entry><entry colname="5" colsep="0" rowsep="0">6.80</entry></row><row valign="bottom"><entry colname="1" colsep="0" rowsep="0" valign="top">353-42-4</entry><entry colname="2" colsep="0" rowsep="0">boron trifluoride dimethyl etherate</entry><entry colname="4" colsep="0" rowsep="0">10</entry><entry colname="5" colsep="0" rowsep="0">6.80</entry></row><row valign="bottom"><entry colname="1" colsep="0" rowsep="0" valign="top">463-51-4</entry><entry colname="2" colsep="0" rowsep="0">ketene</entry><entry colname="4" colsep="0" rowsep="0">1</entry><entry colname="5" colsep="0" rowsep="0">0.22</entry></row><row valign="bottom"><entry colname="1" colsep="0" rowsep="0" valign="top">506-68-3</entry><entry colname="2" colsep="0" rowsep="0">cyanogen bromide</entry><entry colname="4" colsep="0" rowsep="0">10</entry><entry colname="5" colsep="0" rowsep="0">4.50</entry></row><row valign="bottom"><entry colname="1" colsep="0" rowsep="0" valign="top">506-77-4</entry><entry colname="2" colsep="0" rowsep="0">cyanogen chloride</entry><entry colname="4" colsep="0" rowsep="0">10</entry><entry colname="5" colsep="0" rowsep="0">4.50</entry></row><row valign="bottom"><entry colname="1" colsep="0" rowsep="0" valign="top">509-14-8</entry><entry colname="2" colsep="0" rowsep="0">tetranitromethane</entry><entry colname="4" colsep="0" rowsep="0">10</entry><entry colname="5" colsep="0" rowsep="0">4.50</entry></row><row valign="bottom"><entry colname="1" colsep="0" rowsep="0" valign="top">542-88-1</entry><entry colname="2" colsep="0" rowsep="0">dichlorodimethyl ether [bis(chloromethyl) ether]</entry><entry colname="4" colsep="0" rowsep="0">1</entry><entry colname="5" colsep="0" rowsep="0">0.45</entry></row><row valign="bottom"><entry colname="1" colsep="0" rowsep="0" valign="top">556-64-9</entry><entry colname="2" colsep="0" rowsep="0">methyl thiocyanate</entry><entry colname="4" colsep="0" rowsep="0">10</entry><entry colname="5" colsep="0" rowsep="0">9.10</entry></row><row valign="bottom"><entry colname="1" colsep="0" rowsep="0" valign="top">584-84-9</entry><entry colname="2" colsep="0" rowsep="0">toluene-2,4-diisocyanate</entry><entry colname="4" colsep="0" rowsep="0">10</entry><entry colname="5" colsep="0" rowsep="0">4.50</entry></row><row valign="bottom"><entry colname="1" colsep="0" rowsep="0" valign="top">594-42-3</entry><entry colname="2" colsep="0" rowsep="0">perchloromethyl mercaptan</entry><entry colname="4" colsep="0" rowsep="0">10</entry><entry colname="5" colsep="0" rowsep="0">4.50</entry></row><row valign="bottom"><entry colname="1" colsep="0" rowsep="0" valign="top">624-83-9</entry><entry colname="2" colsep="0" rowsep="0">methyl isocyanate</entry><entry colname="4" colsep="0" rowsep="0">10</entry><entry colname="5" colsep="0" rowsep="0">4.50</entry></row><row valign="bottom"><entry colname="1" colsep="0" rowsep="0" valign="top">630-08-0</entry><entry colname="2" colsep="0" rowsep="0">carbon monoxide</entry><entry colname="4" colsep="0" rowsep="0">10</entry><entry colname="5" colsep="0" rowsep="0">6.80</entry></row><row valign="bottom"><entry colname="1" colsep="0" rowsep="0" valign="top">814-68-6</entry><entry colname="2" colsep="0" rowsep="0">acryloyl chloride (acrylyl chloride)</entry><entry colname="4" colsep="0" rowsep="0">10</entry><entry colname="5" colsep="0" rowsep="0">2.27</entry></row><row valign="bottom"><entry colsep="0" rowsep="0" valign="top">2551-62-4</entry><entry colname="2" colsep="0" rowsep="0">sulphur hexafluoride (sulfur hexafluoride)</entry><entry colname="4" colsep="0" rowsep="0">10</entry><entry colname="5" colsep="0" rowsep="0">9.10</entry></row><row valign="bottom"><entry colname="1" colsep="0" rowsep="0" valign="top">4170-30-3</entry><entry colname="2" colsep="0" rowsep="0">crotonaldehyde</entry><entry colname="4" colsep="0" rowsep="0">10</entry><entry colname="5" colsep="0" rowsep="0">9.10</entry></row><row valign="bottom"><entry colname="1" colsep="0" rowsep="0" valign="top">7439-97-6</entry><entry colname="2" colsep="0" rowsep="0">mercury</entry><entry colname="4" colsep="0" rowsep="0">NA</entry><entry colname="5" colsep="0" rowsep="0">1.00</entry></row><row valign="bottom"><entry colname="1" colsep="0" rowsep="0" valign="top">7446-09-5</entry><entry colname="2" colsep="0" rowsep="0">sulphur dioxide</entry><entry colname="4" colsep="0" rowsep="0">10</entry><entry colname="5" colsep="0" rowsep="0">2.27</entry></row><row valign="bottom"><entry colname="1" colsep="0" rowsep="0" valign="top">7446-11-9</entry><entry colname="2" colsep="0" rowsep="0">sulphur trioxide</entry><entry colname="4" colsep="0" rowsep="0">10</entry><entry colname="5" colsep="0" rowsep="0">4.50</entry></row><row valign="bottom"><entry colname="1" colsep="0" rowsep="0" valign="top">7550-45-0</entry><entry colname="2" colsep="0" rowsep="0">titanium tetrachloride</entry><entry colname="4" colsep="0" rowsep="0">10</entry><entry colname="5" colsep="0" rowsep="0">1.13</entry></row><row valign="bottom"><entry colname="1" colsep="0" rowsep="0" valign="top">7616-94-6</entry><entry colname="2" colsep="0" rowsep="0">perchloryl fluoride (trioxychlorofluoride)</entry><entry colname="4" colsep="0" rowsep="0">10</entry><entry colname="5" colsep="0" rowsep="0">6.80</entry></row><row valign="bottom"><entry colname="1" colsep="0" rowsep="0" valign="top">7637-07-2</entry><entry colname="2" colsep="0" rowsep="0">boron trifluoride</entry><entry colname="4" colsep="0" rowsep="0">10</entry><entry colname="5" colsep="0" rowsep="0">2.27</entry></row><row valign="bottom"><entry colname="1" colsep="0" rowsep="0" valign="top">7647-01-0</entry><entry colname="2" colsep="0" rowsep="0">hydrochloric acid</entry><entry colname="4" colsep="0" rowsep="0">30</entry><entry colname="5" colsep="0" rowsep="0">6.80</entry></row><row valign="bottom"><entry colname="1" colsep="0" rowsep="0" valign="top">7647-01-0</entry><entry colname="2" colsep="0" rowsep="0">hydrogen chloride, anhydrous</entry><entry colname="4" colsep="0" rowsep="0">10</entry><entry colname="5" colsep="0" rowsep="0">2.27</entry></row><row valign="bottom"><entry colname="1" colsep="0" rowsep="0" valign="top">7664-39-3</entry><entry colname="2" colsep="0" rowsep="0">hydrofluoric acid</entry><entry colname="4" colsep="0" rowsep="0">50</entry><entry colname="5" colsep="0" rowsep="0">0.45</entry></row><row valign="bottom"><entry colname="1" colsep="0" rowsep="0" valign="top">7664-39-3</entry><entry colname="2" colsep="0" rowsep="0">hydrogen fluoride, anhydrous</entry><entry colname="4" colsep="0" rowsep="0">1</entry><entry colname="5" colsep="0" rowsep="0">0.45</entry></row><row valign="bottom"><entry colname="1" colsep="0" rowsep="0" valign="top">7664-41-7</entry><entry colname="2" colsep="0" rowsep="0">ammonia, anhydrous</entry><entry colname="4" colsep="0" rowsep="0">10</entry><entry colname="5" colsep="0" rowsep="0">4.50</entry></row><row valign="bottom"><entry colname="1" colsep="0" rowsep="0" valign="top">7664-41-7</entry><entry colname="2" colsep="0" rowsep="0">ammonia solution</entry><entry colname="4" colsep="0" rowsep="0">20</entry><entry colname="5" colsep="0" rowsep="0">9.10</entry></row><row valign="bottom"><entry colname="1" colsep="0" rowsep="0" valign="top">7697-37-2</entry><entry colname="2" colsep="0" rowsep="0">nitric acid</entry><entry colname="4" colsep="0" rowsep="0">80</entry><entry colname="5" colsep="0" rowsep="0">6.80</entry></row><row valign="bottom"><entry colname="1" colsep="0" rowsep="0" valign="top">7719-09-7</entry><entry colname="2" colsep="0" rowsep="0">thionyl chloride</entry><entry colname="4" colsep="0" rowsep="0">10</entry><entry colname="5" colsep="0" rowsep="0">6.80</entry></row><row valign="bottom"><entry colname="1" colsep="0" rowsep="0" valign="top">7719-12-2</entry><entry colname="2" colsep="0" rowsep="0">phosphorus trichloride</entry><entry colname="4" colsep="0" rowsep="0">10</entry><entry colname="5" colsep="0" rowsep="0">6.80</entry></row><row valign="bottom"><entry colname="1" colsep="0" rowsep="0" valign="top">7723-14-0</entry><entry colname="2" colsep="0" rowsep="0">phosphorus, white</entry><entry colname="4" colsep="0" rowsep="0">NA</entry><entry colname="5" colsep="0" rowsep="0">1.00</entry></row><row valign="bottom"><entry colname="1" colsep="0" rowsep="0" valign="top">7726-95-6</entry><entry colname="2" colsep="0" rowsep="0">bromine</entry><entry colname="4" colsep="0" rowsep="0">10</entry><entry colname="5" colsep="0" rowsep="0">4.50</entry></row><row valign="bottom"><entry colname="1" colsep="0" rowsep="0" valign="top">7782-41-4</entry><entry colname="2" colsep="0" rowsep="0">fluorine</entry><entry colname="4" colsep="0" rowsep="0">1</entry><entry colname="5" colsep="0" rowsep="0">0.45</entry></row><row valign="bottom"><entry colname="1" colsep="0" rowsep="0" valign="top">7782-50-5</entry><entry colname="2" colsep="0" rowsep="0">chlorine</entry><entry colname="4" colsep="0" rowsep="0">10</entry><entry colname="5" colsep="0" rowsep="0">1.13</entry></row><row valign="bottom"><entry colname="1" colsep="0" rowsep="0" valign="top">7783-06-4</entry><entry colname="2" colsep="0" rowsep="0">hydrogen sulphide</entry><entry colname="4" colsep="0" rowsep="0">10</entry><entry colname="5" colsep="0" rowsep="0">4.50</entry></row><row valign="bottom"><entry colname="1" colsep="0" rowsep="0" valign="top">7783-07-5</entry><entry colname="2" colsep="0" rowsep="0">hydrogen selenide</entry><entry colname="4" colsep="0" rowsep="0">1</entry><entry colname="5" colsep="0" rowsep="0">0.22</entry></row><row valign="bottom"><entry colname="1" colsep="0" rowsep="0" valign="top">7783-60-0</entry><entry colname="2" colsep="0" rowsep="0">sulphur tetrafluoride</entry><entry colname="4" colsep="0" rowsep="0">10</entry><entry colname="5" colsep="0" rowsep="0">1.13</entry></row><row valign="bottom"><entry colname="1" colsep="0" rowsep="0" valign="top">7784-34-1</entry><entry colname="2" colsep="0" rowsep="0">arsenic trichloride (arsenous trichloride)</entry><entry colname="4" colsep="0" rowsep="0">10</entry><entry colname="5" colsep="0" rowsep="0">6.80</entry></row><row valign="bottom"><entry colname="1" colsep="0" rowsep="0" valign="top">7784-42-1</entry><entry colname="2" colsep="0" rowsep="0">arsine</entry><entry colname="4" colsep="0" rowsep="0">1</entry><entry colname="5" colsep="0" rowsep="0">0.45</entry></row><row valign="bottom"><entry colname="1" colsep="0" rowsep="0" valign="top">7790-94-5</entry><entry colname="2" colsep="0" rowsep="0">chlorosulphonic acid</entry><entry colname="4" colsep="0" rowsep="0">10</entry><entry colname="5" colsep="0" rowsep="0">2.27</entry></row><row valign="bottom"><entry colname="1" colsep="0" rowsep="0" valign="top">7803-51-2</entry><entry colname="2" colsep="0" rowsep="0">phosphine</entry><entry colname="4" colsep="0" rowsep="0">10</entry><entry colname="5" colsep="0" rowsep="0">2.27</entry></row><row valign="bottom"><entry colname="1" colsep="0" rowsep="0" valign="top">7803-52-3</entry><entry colname="2" colsep="0" rowsep="0">stibine</entry><entry colname="4" colsep="0" rowsep="0">10</entry><entry colname="5" colsep="0" rowsep="0">2.27</entry></row><row valign="bottom"><entry colname="1" colsep="0" rowsep="0" valign="top">8014-95-7</entry><entry colname="2" colsep="0" rowsep="0">sulphuric acid, fuming (oleum)</entry><entry colname="4" colsep="0" rowsep="0">NA</entry><entry colname="5" colsep="0" rowsep="0">4.50</entry></row><row valign="bottom"><entry colname="1" colsep="0" rowsep="0" valign="top">10025-87-3</entry><entry colname="2" colsep="0" rowsep="0">phosphorus oxychloride</entry><entry colname="4" colsep="0" rowsep="0">10</entry><entry colname="5" colsep="0" rowsep="0">2.27</entry></row><row valign="bottom"><entry colname="1" colsep="0" rowsep="0" valign="top">10035-10-6</entry><entry colname="2" colsep="0" rowsep="0">hydrogen bromide (hydrobromic acid)</entry><entry colname="4" colsep="0" rowsep="0">10</entry><entry colname="5" colsep="0" rowsep="0">1.13</entry></row><row valign="bottom"><entry colname="1" colsep="0" rowsep="0" valign="top">10049-04-4</entry><entry colname="2" colsep="0" rowsep="0">chlorine dioxide</entry><entry colname="4" colsep="0" rowsep="0">1</entry><entry colname="5" colsep="0" rowsep="0">0.45</entry></row><row valign="bottom"><entry colname="1" colsep="0" rowsep="0" valign="top">10102-43-9</entry><entry colname="2" colsep="0" rowsep="0">nitric oxide (nitrogen monoxide)</entry><entry colname="4" colsep="0" rowsep="0">10</entry><entry colname="5" colsep="0" rowsep="0">4.50</entry></row><row valign="bottom"><entry colname="1" colsep="0" rowsep="0" valign="top">10102-44-0</entry><entry colname="2" colsep="0" rowsep="0">nitrogen dioxide</entry><entry colname="4" colsep="0" rowsep="0">10</entry><entry colname="5" colsep="0" rowsep="0">1.13</entry></row><row valign="bottom"><entry colname="1" colsep="0" rowsep="0" valign="top">10294-34-5</entry><entry colname="2" colsep="0" rowsep="0">boron trichloride</entry><entry colname="4" colsep="0" rowsep="0">10</entry><entry colname="5" colsep="0" rowsep="0">2.27</entry></row><row valign="bottom"><entry colname="1" colsep="0" rowsep="0" valign="top">13463-39-3</entry><entry colname="2" colsep="0" rowsep="0">nickel carbonyl</entry><entry colname="4" colsep="0" rowsep="0">1</entry><entry colname="5" colsep="0" rowsep="0">0.45</entry></row><row valign="bottom"><entry colname="1" colsep="0" rowsep="0" valign="top">13463-40-6</entry><entry colname="2" colsep="0" rowsep="0">iron pentacarbonyl</entry><entry colname="4" colsep="0" rowsep="0">10</entry><entry colname="5" colsep="0" rowsep="0">1.13</entry></row><row valign="bottom"><entry colname="1" colsep="0" rowsep="0" valign="top">19287-45-7</entry><entry colname="2" colsep="0" rowsep="0">diborane</entry><entry colname="4" colsep="0" rowsep="0">10</entry><entry colname="5" colsep="0" rowsep="0">1.13</entry></row><row valign="bottom"><entry colname="1" colsep="0" rowsep="0" valign="top">20816-12-0</entry><entry colname="2" colsep="0" rowsep="0">osmium tetroxide</entry><entry colname="4" colsep="0" rowsep="0">1</entry><entry colname="5" colsep="0" rowsep="0">0.22</entry></row><row valign="bottom"><entry colname="1" colsep="0" rowsep="0" valign="top">26471-62-5</entry><entry colname="2" colsep="0" rowsep="0">toluene diisocyanate</entry><entry colname="4" colsep="0" rowsep="0">10</entry><entry colname="5" colsep="0" rowsep="0">4.50</entry></row></tbody></tgroup></table></TableGroup><Heading level="1"><Label>PART 3</Label><TitleText>Other Hazardous Substances</TitleText></Heading><TableGroup pointsize="7" topmarginspacing="4"><table frame="topbot"><tgroup cols="4"><colspec char="." colname="1" colwidth="96.91*" /><colspec char="." colname="2" colwidth="191.57*" /><colspec align="left" char="." charoff="50" colname="4" colwidth="112.54*" /><colspec align="left" char="." charoff="50" colname="5" colwidth="129.65*" /><thead><row topdouble="yes"><entry colsep="0" rowsep="0" valign="top" /><entry colname="2" colsep="0" rowsep="0" valign="top">Column 1</entry><entry colname="4" colsep="0" rowsep="0">Column 2</entry><entry colname="5" colsep="0" rowsep="0">Column 3</entry></row><row valign="bottom"><entry colsep="0" rowsep="1" valign="bottom">CAS Registry Number</entry><entry colsep="0" rowsep="1" valign="bottom">Name of Substance</entry><entry colsep="0" rowsep="1" valign="bottom">Concentration (% by weight)</entry><entry colsep="0" rowsep="1" valign="bottom">Minimum Quantity (metric tonnes)</entry></row></thead><tbody><row valign="bottom"><entry colname="1" colsep="0" rowsep="0" valign="top">56-23-5</entry><entry colname="2" colsep="0" rowsep="0">tetrachloromethane (carbon tetrachloride)</entry><entry colname="4" colsep="0" rowsep="0">1</entry><entry colname="5" colsep="0" rowsep="0">0.22</entry></row><row valign="bottom"><entry colsep="0" rowsep="0" valign="top">79-01-6</entry><entry colsep="0" rowsep="0">trichloroethylene (TCE)</entry><entry colname="4" colsep="0" rowsep="0">1</entry><entry colname="5" colsep="0" rowsep="0">1.13</entry></row><row valign="bottom"><entry colname="1" colsep="0" rowsep="0" valign="top">91-20-3</entry><entry colname="2" colsep="0" rowsep="0">naphthalene (in liquid form)</entry><entry colname="4" colsep="0" rowsep="0">10</entry><entry colname="5" colsep="0" rowsep="0">4.5</entry></row><row valign="bottom"><entry colname="1" colsep="0" rowsep="0" valign="top">91-94-1</entry><entry colname="2" colsep="0" rowsep="0">3,3′-dichlorobenzidine</entry><entry colname="4" colsep="0" rowsep="0">1</entry><entry colname="5" colsep="0" rowsep="0">1.13</entry></row><row valign="bottom"><entry colsep="0" rowsep="0" valign="top">104-40-5</entry><entry colsep="0" rowsep="0">p-nonylphenol</entry><entry colname="4" colsep="0" rowsep="0">10</entry><entry colname="5" colsep="0" rowsep="0">1.13</entry></row><row valign="bottom"><entry colname="1" colsep="0" rowsep="0" valign="top">127-18-4</entry><entry colname="2" colsep="0" rowsep="0">tetrachloroethylene (perchloroethylene)</entry><entry colname="4" colsep="0" rowsep="0">1</entry><entry colname="5" colsep="0" rowsep="0">1.13</entry></row><row valign="bottom"><entry colname="1" colsep="0" rowsep="0" valign="top">373-02-4</entry><entry colname="2" colsep="0" rowsep="0">nickel acetate</entry><entry colname="4" colsep="0" rowsep="0">10</entry><entry colname="5" colsep="0" rowsep="0">0.22</entry></row><row valign="bottom"><entry colname="1" colsep="0" rowsep="0" valign="top">1303-28-2</entry><entry colname="2" colsep="0" rowsep="0">arsenic pentoxide</entry><entry colname="4" colsep="0" rowsep="0">10</entry><entry colname="5" colsep="0" rowsep="0">0.22</entry></row><row valign="bottom"><entry colsep="0" rowsep="0" valign="top">1306-19-0</entry><entry colsep="0" rowsep="0">cadmium oxide</entry><entry colname="4" colsep="0" rowsep="0">10</entry><entry colname="5" colsep="0" rowsep="0">0.22</entry></row><row valign="bottom"><entry colname="1" colsep="0" rowsep="0" valign="top">1306-23-6</entry><entry colname="2" colsep="0" rowsep="0">cadmium sulphide</entry><entry colname="4" colsep="0" rowsep="0">10</entry><entry colname="5" colsep="0" rowsep="0">0.22</entry></row><row valign="bottom"><entry colname="1" colsep="0" rowsep="0" valign="top">1313-99-1</entry><entry colname="2" colsep="0" rowsep="0">nickel oxide</entry><entry colname="4" colsep="0" rowsep="0">10</entry><entry colname="5" colsep="0" rowsep="0">0.22</entry></row><row valign="bottom"><entry colname="1" colsep="0" rowsep="0" valign="top">1327-53-3</entry><entry colname="2" colsep="0" rowsep="0">arsenic trioxide (arsenic(III) oxide)</entry><entry colname="4" colsep="0" rowsep="0">10</entry><entry colname="5" colsep="0" rowsep="0">0.22</entry></row><row valign="bottom"><entry colsep="0" rowsep="0" valign="top">1333-82-0</entry><entry colsep="0" rowsep="0">chromium trioxide</entry><entry colname="4" colsep="0" rowsep="0">10</entry><entry colname="5" colsep="0" rowsep="0">0.22</entry></row><row valign="bottom"><entry colname="1" colsep="0" rowsep="0" valign="top">3333-67-3</entry><entry colname="2" colsep="0" rowsep="0">nickel carbonate</entry><entry colname="4" colsep="0" rowsep="0">10</entry><entry colname="5" colsep="0" rowsep="0">0.22</entry></row><row valign="bottom"><entry colname="1" colsep="0" rowsep="0" valign="top">7440-38-2</entry><entry colname="2" colsep="0" rowsep="0">arsenic</entry><entry colname="4" colsep="0" rowsep="0">10</entry><entry colname="5" colsep="0" rowsep="0">0.22</entry></row><row valign="bottom"><entry colname="1" colsep="0" rowsep="0" valign="top">7718-54-9</entry><entry colname="2" colsep="0" rowsep="0">nickel chloride</entry><entry colname="4" colsep="0" rowsep="0">10</entry><entry colname="5" colsep="0" rowsep="0">0.22</entry></row><row valign="bottom"><entry colsep="0" rowsep="0" valign="top">7738-94-5</entry><entry colsep="0" rowsep="0">chromic acid</entry><entry colname="4" colsep="0" rowsep="0">10</entry><entry colname="5" colsep="0" rowsep="0">0.22</entry></row><row valign="bottom"><entry colname="1" colsep="0" rowsep="0" valign="top">7775-11-3</entry><entry colname="2" colsep="0" rowsep="0">sodium chromate</entry><entry colname="4" colsep="0" rowsep="0">10</entry><entry colname="5" colsep="0" rowsep="0">0.22</entry></row><row valign="bottom"><entry colname="1" colsep="0" rowsep="0" valign="top">7778-39-4</entry><entry colname="2" colsep="0" rowsep="0">arsenic acid</entry><entry colname="4" colsep="0" rowsep="0">10</entry><entry colname="5" colsep="0" rowsep="0">0.22</entry></row><row valign="bottom"><entry colname="1" colsep="0" rowsep="0" valign="top">7778-43-0</entry><entry colname="2" colsep="0" rowsep="0">sodium arsenate, dibasic</entry><entry colname="4" colsep="0" rowsep="0">10</entry><entry colname="5" colsep="0" rowsep="0">0.22</entry></row><row valign="bottom"><entry colname="1" colsep="0" rowsep="0" valign="top">7784-46-5</entry><entry colname="2" colsep="0" rowsep="0">sodium arsenite</entry><entry colname="4" colsep="0" rowsep="0">10</entry><entry colname="5" colsep="0" rowsep="0">0.22</entry></row><row valign="bottom"><entry colname="1" colsep="0" rowsep="0" valign="top">7786-81-4</entry><entry colname="2" colsep="0" rowsep="0">nickel(II) sulphate (nickel(II) sulfate)</entry><entry colname="4" colsep="0" rowsep="0">10</entry><entry colname="5" colsep="0" rowsep="0">0.22</entry></row><row valign="bottom"><entry colname="1" colsep="0" rowsep="0" valign="top">7789-00-6</entry><entry colname="2" colsep="0" rowsep="0">potassium chromate</entry><entry colname="4" colsep="0" rowsep="0">10</entry><entry colname="5" colsep="0" rowsep="0">0.22</entry></row><row valign="bottom"><entry colsep="0" rowsep="0" valign="top">10048-95-0</entry><entry colsep="0" rowsep="0">sodium arsenate, dibasic, heptahydrate</entry><entry colname="4" colsep="0" rowsep="0">10</entry><entry colname="5" colsep="0" rowsep="0">0.22</entry></row><row valign="bottom"><entry colsep="0" rowsep="0" valign="top">10101-97-0</entry><entry colsep="0" rowsep="0">nickel(II) sulphate, hexahydrate (nickel(II) sulfate, hexahydrate)</entry><entry colname="4" colsep="0" rowsep="0">10</entry><entry colname="5" colsep="0" rowsep="0">0.22</entry></row><row valign="bottom"><entry colname="1" colsep="0" rowsep="0" valign="top">10108-64-2</entry><entry colname="2" colsep="0" rowsep="0">cadmium chloride</entry><entry colname="4" colsep="0" rowsep="0">10</entry><entry colname="5" colsep="0" rowsep="0">0.22</entry></row><row valign="bottom"><entry colname="1" colsep="0" rowsep="0" valign="top">10124-36-4</entry><entry colname="2" colsep="0" rowsep="0">cadmium sulphate</entry><entry colname="4" colsep="0" rowsep="0">10</entry><entry colname="5" colsep="0" rowsep="0">0.22</entry></row><row valign="bottom"><entry colname="1" colsep="0" rowsep="0" valign="top">10588-01-9</entry><entry colname="2" colsep="0" rowsep="0">sodium dichromate</entry><entry colname="4" colsep="0" rowsep="0">10</entry><entry colname="5" colsep="0" rowsep="0">0.22</entry></row><row valign="bottom"><entry colname="1" colsep="0" rowsep="0" valign="top">13138-45-9</entry><entry colname="2" colsep="0" rowsep="0">nickel nitrate (nickel(II) nitrate)</entry><entry colname="4" colsep="0" rowsep="0">10</entry><entry colname="5" colsep="0" rowsep="0">0.22</entry></row><row valign="bottom"><entry colsep="0" rowsep="0" valign="top">13478-00-7</entry><entry colsep="0" rowsep="0">nickel(II) nitrate, hexahydrate</entry><entry colname="4" colsep="0" rowsep="0">10</entry><entry colname="5" colsep="0" rowsep="0">0.22</entry></row><row valign="bottom"><entry colname="1" colsep="0" rowsep="0" valign="top">15699-18-0</entry><entry colname="2" colsep="0" rowsep="0">nickel ammonium sulphate (nickel ammonium sulfate)</entry><entry colname="4" colsep="0" rowsep="0">10</entry><entry colname="5" colsep="0" rowsep="0">0.22</entry></row><row valign="bottom"><entry colsep="0" rowsep="0" valign="top">25154-52-3</entry><entry colsep="0" rowsep="0">nonylphenol (mixed isomer)</entry><entry colname="4" colsep="0" rowsep="0">10</entry><entry colname="5" colsep="0" rowsep="0">1.13</entry></row><row valign="bottom"><entry colsep="0" rowsep="0" valign="top">81741-28-8</entry><entry colsep="0" rowsep="0">tributyl tetradecyl phosphonium chloride (TTPC)</entry><entry colname="4" colsep="0" rowsep="0">10</entry><entry colname="5" colsep="0" rowsep="0">0.22</entry></row><row valign="bottom"><entry colname="1" colsep="0" rowsep="0" valign="top">84852-15-3</entry><entry colname="2" colsep="0" rowsep="0">4-<Emphasis style="italic">tert</Emphasis>-nonylphenol</entry><entry colname="4" colsep="0" rowsep="0">10</entry><entry colname="5" colsep="0" rowsep="0">1.13</entry></row></tbody></tgroup></table></TableGroup><Provision format-ref="indent-0-0"><Text>Note: The percentage concentration in column 2 is the percentage concentration based on the proportion of the weight of the substance to the weight of the mixture.</Text></Provision><HistoricalNote>SOR/2011-294, s. 8.</HistoricalNote></Schedule><Schedule bilingual="no" spanlanguages="no"><ScheduleFormHeading><Label>SCHEDULE 2</Label><OriginatingRef>(Subsections 3(1), (4) and 4(1))</OriginatingRef><TitleText>Information To Be Submitted in the Notice Regarding the Identification of Substance and Place</TitleText></ScheduleFormHeading><RegulationPiece><Section><Label>1</Label><Text>Place where one or more substances are located:</Text><Paragraph><Label>(a)</Label><Text>a description of the place or the facility name (if applicable), civic address and location by latitude and longitude; and</Text></Paragraph><Paragraph><Label>(b)</Label><Text>the names, position titles, e-mail addresses (if any), telephone numbers and fax numbers (if any) of the contact person and their alternate.</Text></Paragraph></Section><Section><Label>2</Label><Text>Head office (if different from above):</Text><Paragraph><Label>(a)</Label><Text>name and address; and</Text></Paragraph><Paragraph><Label>(b)</Label><Text>the names, position titles, e-mail addresses (if any), telephone numbers and fax numbers (if any) of the contact person and their alternate.</Text></Paragraph></Section><Section><Label>3</Label><Text>For each substance located at the place:</Text><Paragraph><Label>(a)</Label><Text>the name of the substance;</Text></Paragraph><Paragraph><Label>(b)</Label><Text>the CAS registry number;</Text></Paragraph><Paragraph><Label>(c)</Label><Text>the UN number (if applicable);</Text></Paragraph><Paragraph><Label>(d)</Label><Text>the maximum expected quantity of the substance at any time during the calendar year;</Text></Paragraph><Paragraph><Label>(e)</Label><Text>the maximum capacity of the largest container in which the substance is stored;</Text></Paragraph><Paragraph><Label>(f)</Label><Text>the maximum expected quantity of the mixture (if applicable); and</Text></Paragraph><Paragraph><Label>(g)</Label><Text>the concentration of the substance within the mixture (if applicable).</Text></Paragraph></Section></RegulationPiece><HistoricalNote>SOR/2011-294, ss. 9 to 12.</HistoricalNote></Schedule><Schedule bilingual="no" spanlanguages="no"><ScheduleFormHeading><Label>SCHEDULE 3</Label><OriginatingRef>(Subsections 3(6), 4(5) and 5(2))</OriginatingRef><TitleText>Certification</TitleText></ScheduleFormHeading><TableGroup bilingual="no" pointsize="9" rowbreak="no" spanlanguages="no" spanmarginalnotecol="no" topmarginspacing="6"><table frame="none"><tgroup cols="2"><colspec colname="1" colwidth="324.55*" /><colspec colname="COLSPEC1" colwidth="611.45*" /><tbody><row rowsep="0"><entry nameend="COLSPEC1" namest="1" valign="top">I hereby certify that the information provided with respect to Schedule <Leader leader="solid" length="3pc" /> to the <XRefExternal reference-type="regulation">Environmental Emergency Regulations</XRefExternal> is accurate and complete.</entry></row><row rowsep="0" topmarginspacing="6"><entry nameend="COLSPEC1" namest="1" valign="top"><SignatureBlock width="18pc"><SignatureLine><Leader leader="solid" /></SignatureLine><SignatureName topmarginspacing="0">(<Emphasis style="italic">Signature of the person or duly authorized representative</Emphasis>)</SignatureName></SignatureBlock></entry></row><row rowsep="0" topmarginspacing="6"><entry colname="1" colsep="0" valign="top">Name (<Emphasis style="italic">please print</Emphasis>):</entry><entry colsep="0"><LeaderRightJustified leader="solid" /></entry></row><row rowsep="0" topmarginspacing="6"><entry colname="1" colsep="0" valign="top">Title:</entry><entry colsep="0"><LeaderRightJustified leader="solid" /></entry></row><row rowsep="0"><entry colname="1" colsep="0" valign="top">Date:</entry><entry colsep="0"><LeaderRightJustified leader="solid" /></entry></row></tbody></tgroup></table></TableGroup></Schedule><Schedule bilingual="no" spanlanguages="no"><ScheduleFormHeading><Label>SCHEDULE 4</Label><OriginatingRef>(Subsections 4(4) and 7(3))</OriginatingRef><TitleText>Information To Be Submitted in the Report Regarding the Preparation of an Environmental Emergency Plan</TitleText></ScheduleFormHeading><RegulationPiece><Section><Label>1</Label><Text>Place where one or more substances are located:</Text><Paragraph><Label>(a)</Label><Text>a description of the place or the facility name (if applicable), civic address and location by latitude and longitude; and</Text></Paragraph><Paragraph><Label>(b)</Label><Text>the name of each substance.</Text></Paragraph></Section><Section><Label>2</Label><Text>Use of prior plans:</Text><Paragraph><Label>(a)</Label><Text>indicate whether the environmental emergency plan was based on a plan prepared on a voluntary basis;</Text></Paragraph><Paragraph><Label>(b)</Label><Text>indicate whether the environmental emergency plan was based on a plan prepared for another government and provide particulars, if applicable; and</Text></Paragraph><Paragraph><Label>(c)</Label><Text>indicate whether the environmental emergency plan was based on a plan prepared under another Act of Parliament and provide particulars, if applicable.</Text></Paragraph></Section><Section><Label>3</Label><Text>Local-level involvement:</Text><Paragraph><Label>(a)</Label><Text>give the name of the local authorities, community or interest groups that have been involved in the plan’s development, if any; and</Text></Paragraph><Paragraph><Label>(b)</Label><Text>identify whether the plan or its relevant parts were made available to the appropriate local authorities (such as police and fire departments) that may be involved in an emergency response.</Text></Paragraph></Section><Section><Label>4</Label><Text>Information for each substance covered by an environmental emergency plan:</Text><Paragraph><Label>(a)</Label><Text>the name, CAS registry number and UN number (if applicable) of the substance; and</Text></Paragraph><Paragraph><Label>(b)</Label><Text>the nature of activities at the place where the substance is located.</Text></Paragraph></Section><Section><Label>5</Label><Text>The date on which the preparation of the environmental emergency plan or an amendment to the plan referred to in subsection 7(2) was completed.</Text></Section><Section><Label>6</Label><Text>The location of the environmental emergency plan if it is different from the place where one or more substances are located.</Text></Section></RegulationPiece><HistoricalNote>SOR/2011-294, ss. 13 to 15.</HistoricalNote></Schedule><Schedule bilingual="no" spanlanguages="no"><ScheduleFormHeading><Label>SCHEDULE 5</Label><OriginatingRef>(Subsection 5(1))</OriginatingRef><TitleText>Information To Be Submitted in the Notice of the Implementation and Testing of an Environmental Emergency Plan</TitleText></ScheduleFormHeading><RegulationPiece><Section><Label>1</Label><Text>Place where one or more substances are located:</Text><Paragraph><Label>(a)</Label><Text>a description of the place or the facility name (if applicable), civic address and location by latitude and longitude; and</Text></Paragraph><Paragraph><Label>(b)</Label><Text>the name of each substance.</Text></Paragraph></Section><Section><Label>2</Label><Text>The implementation and testing of the environmental emergency plan for the substances mentioned in section 1:</Text><Paragraph><Label>(a)</Label><Text>the date of testing; and</Text></Paragraph><Paragraph><Label>(b)</Label><Text>the list of all local authorities, community or interest groups, if any, that have been involved in the testing of the plan.</Text></Paragraph></Section></RegulationPiece><HistoricalNote>SOR/2011-294, s. 16.</HistoricalNote></Schedule><Schedule spanlanguages="no" bilingual="no"><ScheduleFormHeading><Label>SCHEDULE 6</Label><OriginatingRef>(Subsection 3(5.1))</OriginatingRef><TitleText>Information To Be Submitted in the Notice of Closure or Decommissioning</TitleText></ScheduleFormHeading><RegulationPiece><Section><Label>1</Label><Text>Place where one or more substances are located:</Text><Paragraph><Label>(a) </Label><Text>a description of the place or the facility name (if applicable), civic address and location by latitude and longitude;</Text></Paragraph><Paragraph><Label>(b) </Label><Text>the name of each substance;</Text></Paragraph><Paragraph><Label>(c) </Label><Text>the quantity of each substance remaining at the place or facility; and</Text></Paragraph><Paragraph><Label>(d) </Label><Text>the names, position titles, e-mail address (if any), telephone numbers and fax numbers (if any) of the contact person and their alternate.</Text></Paragraph></Section><Section><Label>2</Label><Text>The closing or decommissioning date for the facility or place.</Text></Section><Section><Label>3</Label><Text>A description of the measures taken to prevent and to respond to an environmental emergency when the facility or place closes or is decommissioned.</Text></Section></RegulationPiece><HistoricalNote>SOR/2011-294, s. 17.</HistoricalNote></Schedule></Regulation>